{
  "confirmed": true,
  "home": {
    "players": [
      {
        "player": {
          "name": "Weverton",
          "slug": "weverton",
          "shortName": "Weverton",
          "position": "G",
          "jerseyNumber": "21",
          "userCount": 2685,
          "id": 243529,
          "country": {
            "alpha2": "BR",
            "name": "Brazil"
          },
          "marketValueCurrency": "EUR",
          "dateOfBirthTimestamp": 566352000,
          "fieldTranslations": {
            "nameTranslation": {
              "ar": "ويفرتون"
            },
            "shortNameTranslation": {}
          }
        },
        "shirtNumber": 1,
        "jerseyNumber": "1",
        "position": "G",
        "substitute": false,
        "captain": true,
        "statistics": {
          "totalPass": 30,
          "accuratePass": 18,
          "totalLongBalls": 16,
          "accurateLongBalls": 4,
          "aerialWon": 1,
          "duelWon": 1,
          "totalClearance": 1,
          "savedShotsFromInsideTheBox": 1,
          "saves": 2,
          "punches": 1,
          "minutesPlayed": 90,
          "touches": 36,
          "rating": 7.4,
          "possessionLostCtrl": 12,
          "penaltyShootoutSave": 2
        }
      },
      {
        "player": {
          "name": "Marcos Rocha",
          "firstName": "",
          "lastName": "",
          "slug": "marcos-rocha",
          "shortName": "Marcos Rocha",
          "position": "D",
          "jerseyNumber": "2",
          "userCount": 976,
          "id": 82576,
          "country": {
            "alpha2": "BR",
            "name": "Brazil"
          },
          "marketValueCurrency": "EUR",
          "dateOfBirthTimestamp": 597801600
        },
        "shirtNumber": 2,
        "jerseyNumber": "2",
        "position": "D",
        "substitute": false,
        "statistics": {
          "totalPass": 34,
          "accuratePass": 25,
          "totalLongBalls": 5,
          "accurateLongBalls": 4,
          "totalCross": 1,
          "accurateCross": 1,
          "aerialLost": 2,
          "aerialWon": 3,
          "duelLost": 3,
          "duelWon": 6,
          "totalClearance": 3,
          "interceptionWon": 2,
          "totalTackle": 3,
          "fouls": 1,
          "minutesPlayed": 90,
          "touches": 60,
          "rating": 7.4,
          "possessionLostCtrl": 14
        }
      },
      {
        "player": {
          "name": "Felipe Melo",
          "slug": "felipe-melo",
          "shortName": "F. Melo",
          "position": "D",
          "jerseyNumber": "30",
          "userCount": 1449,
          "id": 4811,
          "country": {
            "alpha2": "BR",
            "name": "Brazil"
          },
          "marketValueCurrency": "EUR",
          "dateOfBirthTimestamp": 425433600
        },
        "shirtNumber": 30,
        "jerseyNumber": "30",
        "position": "D",
        "substitute": false,
        "statistics": {
          "totalPass": 34,
          "accuratePass": 29,
          "totalLongBalls": 8,
          "accurateLongBalls": 4,
          "aerialWon": 4,
          "duelLost": 1,
          "duelWon": 6,
          "challengeLost": 1,
          "totalClearance": 3,
          "outfielderBlock": 2,
          "totalTackle": 2,
          "minutesPlayed": 90,
          "touches": 42,
          "rating": 7,
          "possessionLostCtrl": 6
        }
      },
      {
        "player": {
          "name": "Gustavo Gómez",
          "firstName": "",
          "lastName": "",
          "slug": "gustavo-gomez",
          "shortName": "G. Gómez",
          "position": "D",
          "jerseyNumber": "15",
          "userCount": 2799,
          "id": 220833,
          "country": {
            "alpha2": "PY",
            "name": "Paraguay"
          },
          "marketValueCurrency": "EUR",
          "dateOfBirthTimestamp": 736646400,
          "fieldTranslations": {
            "nameTranslation": {
              "ar": "غوميز"
            },
            "shortNameTranslation": {}
          }
        },
        "shirtNumber": 15,
        "jerseyNumber": "15",
        "position": "D",
        "substitute": false,
        "statistics": {
          "totalPass": 29,
          "accuratePass": 26,
          "totalLongBalls": 5,
          "accurateLongBalls": 4,
          "aerialLost": 3,
          "aerialWon": 7,
          "duelLost": 6,
          "duelWon": 8,
          "challengeLost": 1,
          "onTargetScoringAttempt": 1,
          "totalClearance": 8,
          "outfielderBlock": 2,
          "interceptionWon": 2,
          "totalTackle": 1,
          "errorLeadToAGoal": 1,
          "penaltyConceded": 1,
          "wasFouled": 2,
          "fouls": 2,
          "minutesPlayed": 90,
          "touches": 47,
          "rating": 6.5,
          "possessionLostCtrl": 4
        }
      },
      {
        "player": {
          "name": "Matías Viña",
          "slug": "matias-vina",
          "shortName": "M. Viña",
          "position": "D",
          "jerseyNumber": "17",
          "userCount": 1941,
          "id": 875295,
          "country": {
            "alpha2": "UY",
            "name": "Uruguay"
          },
          "marketValueCurrency": "EUR",
          "dateOfBirthTimestamp": 879033600,
          "fieldTranslations": {
            "nameTranslation": {
              "ar": "فينا, ماتياس"
            },
            "shortNameTranslation": {}
          }
        },
        "shirtNumber": 17,
        "jerseyNumber": "17",
        "position": "D",
        "substitute": false,
        "statistics": {
          "totalPass": 32,
          "accuratePass": 27,
          "totalLongBalls": 6,
          "accurateLongBalls": 3,
          "goalAssist": 1,
          "totalCross": 4,
          "accurateCross": 1,
          "aerialLost": 2,
          "aerialWon": 2,
          "duelLost": 5,
          "duelWon": 4,
          "dispossessed": 1,
          "totalContest": 2,
          "wonContest": 1,
          "totalClearance": 3,
          "interceptionWon": 1,
          "wasFouled": 1,
          "fouls": 2,
          "minutesPlayed": 90,
          "touches": 60,
          "rating": 6.9,
          "possessionLostCtrl": 17,
          "keyPass": 2
        }
      },
      {
        "player": {
          "name": "Ramires",
          "slug": "ramires",
          "shortName": "Ramires",
          "position": "M",
          "jerseyNumber": "7",
          "userCount": 309,
          "id": 33110,
          "country": {
            "alpha2": "BR",
            "name": "Brazil"
          },
          "marketValueCurrency": "EUR",
          "dateOfBirthTimestamp": 543542400
        },
        "shirtNumber": 18,
        "jerseyNumber": "18",
        "position": "M",
        "substitute": false,
        "statistics": {
          "totalPass": 16,
          "accuratePass": 13,
          "totalLongBalls": 3,
          "accurateLongBalls": 3,
          "totalCross": 1,
          "aerialWon": 1,
          "duelWon": 2,
          "totalContest": 1,
          "wonContest": 1,
          "blockedScoringAttempt": 1,
          "totalOffside": 1,
          "minutesPlayed": 45,
          "touches": 19,
          "rating": 6.8,
          "possessionLostCtrl": 4
        }
      },
      {
        "player": {
          "name": "Patrick de Paula",
          "firstName": "",
          "lastName": "",
          "slug": "patrick-de-paula",
          "shortName": "Patrick de Paula",
          "position": "M",
          "jerseyNumber": "8",
          "userCount": 729,
          "id": 1015291,
          "country": {
            "alpha2": "BR",
            "name": "Brazil"
          },
          "marketValueCurrency": "EUR",
          "dateOfBirthTimestamp": 936748800
        },
        "shirtNumber": 5,
        "jerseyNumber": "5",
        "position": "M",
        "substitute": false,
        "statistics": {
          "totalPass": 42,
          "accuratePass": 35,
          "totalLongBalls": 8,
          "accurateLongBalls": 6,
          "totalCross": 3,
          "aerialLost": 1,
          "aerialWon": 2,
          "duelLost": 4,
          "duelWon": 4,
          "totalContest": 2,
          "wonContest": 1,
          "shotOffTarget": 1,
          "outfielderBlock": 1,
          "interceptionWon": 1,
          "totalTackle": 1,
          "fouls": 2,
          "minutesPlayed": 90,
          "touches": 54,
          "rating": 7.1,
          "possessionLostCtrl": 13,
          "penaltyShootoutGoal": 1
        }
      },
      {
        "player": {
          "name": "Gabriel Menino",
          "firstName": "",
          "lastName": "",
          "slug": "gabriel-menino",
          "shortName": "Gabriel Menino",
          "position": "M",
          "jerseyNumber": "25",
          "userCount": 1987,
          "id": 974556,
          "country": {
            "alpha2": "BR",
            "name": "Brazil"
          },
          "marketValueCurrency": "EUR",
          "dateOfBirthTimestamp": 970185600
        },
        "shirtNumber": 25,
        "jerseyNumber": "25",
        "position": "M",
        "substitute": false,
        "statistics": {
          "totalPass": 21,
          "accuratePass": 19,
          "totalLongBalls": 3,
          "accurateLongBalls": 3,
          "totalCross": 4,
          "duelLost": 2,
          "duelWon": 3,
          "dispossessed": 1,
          "totalContest": 1,
          "wonContest": 1,
          "interceptionWon": 1,
          "totalTackle": 1,
          "wasFouled": 1,
          "fouls": 1,
          "minutesPlayed": 45,
          "touches": 32,
          "rating": 6.9,
          "possessionLostCtrl": 8
        }
      },
      {
        "player": {
          "name": "Willian",
          "firstName": "",
          "lastName": "",
          "slug": "willian",
          "shortName": "Willian",
          "position": "F",
          "jerseyNumber": "11",
          "userCount": 606,
          "id": 146308,
          "country": {
            "alpha2": "BR",
            "name": "Brazil"
          },
          "marketValueCurrency": "EUR",
          "dateOfBirthTimestamp": 532742400,
          "fieldTranslations": {
            "nameTranslation": {
              "ar": "ويليان"
            },
            "shortNameTranslation": {}
          }
        },
        "shirtNumber": 29,
        "jerseyNumber": "29",
        "position": "F",
        "substitute": false,
        "statistics": {
          "totalPass": 16,
          "accuratePass": 13,
          "totalLongBalls": 3,
          "accurateLongBalls": 1,
          "totalCross": 1,
          "duelLost": 2,
          "duelWon": 1,
          "dispossessed": 1,
          "bigChanceMissed": 1,
          "onTargetScoringAttempt": 1,
          "totalClearance": 2,
          "wasFouled": 1,
          "fouls": 1,
          "minutesPlayed": 85,
          "touches": 26,
          "rating": 6.4,
          "possessionLostCtrl": 8,
          "keyPass": 1
        }
      },
      {
        "player": {
          "name": "Luiz Adriano",
          "firstName": "",
          "lastName": "",
          "slug": "luiz-adriano",
          "shortName": "L. Adriano",
          "position": "F",
          "jerseyNumber": "9",
          "userCount": 763,
          "id": 39438,
          "country": {
            "alpha2": "BR",
            "name": "Brazil"
          },
          "marketValueCurrency": "EUR",
          "dateOfBirthTimestamp": 545184000
        },
        "shirtNumber": 10,
        "jerseyNumber": "10",
        "position": "F",
        "substitute": false,
        "statistics": {
          "totalPass": 19,
          "accuratePass": 15,
          "aerialLost": 4,
          "aerialWon": 4,
          "duelLost": 7,
          "duelWon": 6,
          "dispossessed": 2,
          "onTargetScoringAttempt": 1,
          "goals": 1,
          "wasFouled": 2,
          "fouls": 2,
          "minutesPlayed": 77,
          "touches": 26,
          "rating": 7.4,
          "possessionLostCtrl": 7,
          "keyPass": 2
        }
      },
      {
        "player": {
          "name": "Zé Rafael",
          "slug": "ze-rafael",
          "shortName": "Z. Rafael",
          "position": "M",
          "jerseyNumber": "8",
          "userCount": 1391,
          "id": 329069,
          "country": {
            "alpha2": "BR",
            "name": "Brazil"
          },
          "marketValueCurrency": "EUR",
          "dateOfBirthTimestamp": 740188800
        },
        "shirtNumber": 8,
        "jerseyNumber": "8",
        "position": "F",
        "substitute": false,
        "statistics": {
          "totalPass": 24,
          "accuratePass": 18,
          "totalLongBalls": 2,
          "accurateLongBalls": 1,
          "totalCross": 1,
          "aerialWon": 1,
          "duelLost": 6,
          "duelWon": 7,
          "totalContest": 2,
          "wonContest": 1,
          "bigChanceCreated": 1,
          "shotOffTarget": 1,
          "blockedScoringAttempt": 1,
          "totalClearance": 1,
          "interceptionWon": 1,
          "totalTackle": 4,
          "wasFouled": 1,
          "fouls": 5,
          "minutesPlayed": 76,
          "touches": 39,
          "rating": 7.4,
          "possessionLostCtrl": 10,
          "keyPass": 1
        }
      },
      {
        "player": {
          "name": "Bruno Henrique",
          "slug": "bruno-henrique",
          "shortName": "Bruno Henrique",
          "position": "M",
          "jerseyNumber": "8",
          "userCount": 389,
          "id": 345113,
          "country": {
            "alpha2": "BR",
            "name": "Brazil"
          },
          "marketValueCurrency": "EUR",
          "dateOfBirthTimestamp": 624931200,
          "fieldTranslations": {
            "nameTranslation": {
              "ar": "برونو هنريك"
            },
            "shortNameTranslation": {}
          }
        },
        "shirtNumber": 19,
        "jerseyNumber": "19",
        "position": "M",
        "substitute": true,
        "statistics": {
          "totalPass": 12,
          "accuratePass": 10,
          "totalLongBalls": 2,
          "shotOffTarget": 1,
          "minutesPlayed": 45,
          "touches": 13,
          "rating": 6.2,
          "possessionLostCtrl": 2,
          "penaltyShootoutMiss": 1
        }
      },
      {
        "player": {
          "name": "Rony",
          "firstName": "",
          "lastName": "",
          "slug": "rony",
          "shortName": "Rony",
          "position": "F",
          "jerseyNumber": "10",
          "userCount": 3832,
          "id": 835260,
          "country": {
            "alpha2": "BR",
            "name": "Brazil"
          },
          "marketValueCurrency": "EUR",
          "dateOfBirthTimestamp": 800150400,
          "fieldTranslations": {
            "nameTranslation": {
              "ar": "روني"
            },
            "shortNameTranslation": {}
          }
        },
        "shirtNumber": 11,
        "jerseyNumber": "11",
        "position": "M",
        "substitute": true,
        "statistics": {
          "totalPass": 14,
          "accuratePass": 14,
          "totalLongBalls": 1,
          "accurateLongBalls": 1,
          "totalCross": 3,
          "aerialLost": 1,
          "aerialWon": 1,
          "duelLost": 5,
          "duelWon": 4,
          "dispossessed": 1,
          "totalContest": 3,
          "wonContest": 1,
          "shotOffTarget": 1,
          "blockedScoringAttempt": 1,
          "interceptionWon": 1,
          "wasFouled": 2,
          "fouls": 1,
          "minutesPlayed": 45,
          "touches": 31,
          "rating": 6.4,
          "possessionLostCtrl": 9
        }
      },
      {
        "player": {
          "name": "Raphael Veiga",
          "firstName": "",
          "lastName": "",
          "slug": "raphael-veiga",
          "shortName": "Raphael Veiga",
          "position": "M",
          "jerseyNumber": "23",
          "userCount": 8015,
          "id": 840020,
          "country": {
            "alpha2": "BR",
            "name": "Brazil"
          },
          "marketValueCurrency": "EUR",
          "dateOfBirthTimestamp": 803520000,
          "fieldTranslations": {
            "nameTranslation": {
              "ar": "رافائيل فييغا"
            },
            "shortNameTranslation": {}
          }
        },
        "shirtNumber": 23,
        "jerseyNumber": "23",
        "position": "M",
        "substitute": true,
        "statistics": {
          "totalPass": 2,
          "accuratePass": 2,
          "totalCross": 1,
          "duelLost": 1,
          "dispossessed": 1,
          "minutesPlayed": 14,
          "touches": 7,
          "rating": 6.5,
          "possessionLostCtrl": 3,
          "penaltyShootoutGoal": 1
        }
      },
      {
        "player": {
          "name": "Gustavo Scarpa",
          "firstName": "",
          "lastName": "",
          "slug": "gustavo-scarpa",
          "shortName": "Gustavo Scarpa",
          "position": "M",
          "jerseyNumber": "31",
          "userCount": 6377,
          "id": 559036,
          "country": {
            "alpha2": "BR",
            "name": "Brazil"
          },
          "marketValueCurrency": "EUR",
          "dateOfBirthTimestamp": 757728000,
          "fieldTranslations": {
            "nameTranslation": {
              "ar": "سكاربا, غوستافو"
            },
            "shortNameTranslation": {}
          }
        },
        "shirtNumber": 14,
        "jerseyNumber": "14",
        "position": "M",
        "substitute": true,
        "statistics": {
          "totalPass": 6,
          "accuratePass": 3,
          "totalLongBalls": 1,
          "totalCross": 2,
          "accurateCross": 2,
          "aerialLost": 1,
          "duelLost": 2,
          "duelWon": 1,
          "shotOffTarget": 1,
          "totalTackle": 1,
          "fouls": 1,
          "minutesPlayed": 13,
          "touches": 12,
          "rating": 7.1,
          "possessionLostCtrl": 4,
          "penaltyShootoutGoal": 1,
          "keyPass": 1
        }
      },
      {
        "player": {
          "name": "Lucas Lima",
          "slug": "lucas-lima",
          "shortName": "L. Lima",
          "position": "M",
          "jerseyNumber": "23",
          "userCount": 988,
          "id": 244589,
          "country": {
            "alpha2": "BR",
            "name": "Brazil"
          },
          "marketValueCurrency": "EUR",
          "dateOfBirthTimestamp": 647481600
        },
        "shirtNumber": 20,
        "jerseyNumber": "20",
        "position": "M",
        "substitute": true,
        "statistics": {
          "totalPass": 2,
          "accuratePass": 2,
          "totalLongBalls": 1,
          "accurateLongBalls": 1,
          "duelLost": 1,
          "fouls": 1,
          "minutesPlayed": 13,
          "touches": 2,
          "rating": 6.7,
          "penaltyShootoutGoal": 1,
          "keyPass": 1
        }
      },
      {
        "player": {
          "name": "Jailson",
          "slug": "jailson",
          "shortName": "Jailson",
          "position": "G",
          "jerseyNumber": "49",
          "userCount": 228,
          "id": 25263,
          "country": {
            "alpha2": "BR",
            "name": "Brazil"
          },
          "marketValueCurrency": "EUR",
          "dateOfBirthTimestamp": 364435200
        },
        "shirtNumber": 42,
        "jerseyNumber": "42",
        "position": "G",
        "substitute": true,
        "statistics": {}
      },
      {
        "player": {
          "name": "Vitor Hugo",
          "slug": "vitor-hugo",
          "shortName": "V. Hugo",
          "position": "D",
          "jerseyNumber": "31",
          "userCount": 340,
          "id": 794838,
          "country": {
            "alpha2": "BR",
            "name": "Brazil"
          },
          "marketValueCurrency": "EUR",
          "dateOfBirthTimestamp": 674697600,
          "fieldTranslations": {
            "nameTranslation": {
              "ar": "هوغو, فيتور"
            },
            "shortNameTranslation": {}
          }
        },
        "shirtNumber": 4,
        "jerseyNumber": "4",
        "position": "D",
        "substitute": true,
        "statistics": {}
      },
      {
        "player": {
          "name": "Diogo Barbosa",
          "slug": "diogo-barbosa",
          "shortName": "Diogo Barbosa",
          "position": "D",
          "jerseyNumber": "40",
          "userCount": 343,
          "id": 243107,
          "country": {
            "alpha2": "BR",
            "name": "Brazil"
          },
          "marketValueCurrency": "EUR",
          "dateOfBirthTimestamp": 714009600
        },
        "shirtNumber": 6,
        "jerseyNumber": "6",
        "position": "D",
        "substitute": true,
        "statistics": {}
      },
      {
        "player": {
          "name": "Luan",
          "firstName": "",
          "lastName": "",
          "slug": "luan",
          "shortName": "Luan",
          "position": "D",
          "jerseyNumber": "13",
          "userCount": 759,
          "id": 250351,
          "country": {
            "alpha2": "BR",
            "name": "Brazil"
          },
          "marketValueCurrency": "EUR",
          "dateOfBirthTimestamp": 736992000
        },
        "shirtNumber": 13,
        "jerseyNumber": "13",
        "position": "D",
        "substitute": true,
        "statistics": {}
      },
      {
        "player": {
          "name": "Mayke",
          "slug": "mayke",
          "shortName": "Mayke",
          "position": "D",
          "jerseyNumber": "12",
          "userCount": 937,
          "id": 273329,
          "country": {
            "alpha2": "BR",
            "name": "Brazil"
          },
          "marketValueCurrency": "EUR",
          "dateOfBirthTimestamp": 721353600,
          "fieldTranslations": {
            "nameTranslation": {
              "ar": "مايكي"
            },
            "shortNameTranslation": {}
          }
        },
        "shirtNumber": 12,
        "jerseyNumber": "12",
        "position": "D",
        "substitute": true,
        "statistics": {}
      },
      {
        "player": {
          "name": "Gabriel Silva",
          "firstName": "Gabriel Silva",
          "lastName": "",
          "slug": "gabriel-silva",
          "shortName": "Gabriel Silva",
          "position": "M",
          "jerseyNumber": "49",
          "userCount": 387,
          "id": 1046794,
          "country": {
            "alpha2": "BR",
            "name": "Brazil"
          },
          "marketValueCurrency": "EUR",
          "dateOfBirthTimestamp": 1016755200
        },
        "shirtNumber": 49,
        "jerseyNumber": "49",
        "position": "F",
        "substitute": true,
        "statistics": {}
      },
      {
        "player": {
          "name": "Iván Angulo",
          "slug": "ivan-angulo",
          "shortName": "I. Angulo",
          "position": "M",
          "jerseyNumber": "77",
          "userCount": 288,
          "id": 861493,
          "country": {
            "alpha2": "CO",
            "name": "Colombia"
          },
          "marketValueCurrency": "EUR",
          "dateOfBirthTimestamp": 922060800
        },
        "shirtNumber": 38,
        "jerseyNumber": "38",
        "position": "M",
        "substitute": true,
        "statistics": {}
      }
    ],
    "supportStaff": [],
    "formation": "4-3-3",
    "playerColor": {
      "primary": "339966",
      "number": "ffffff",
      "outline": "339966",
      "fancyNumber": "222226"
    },
    "goalkeeperColor": {
      "primary": "000099",
      "number": "ffffff",
      "outline": "000099",
      "fancyNumber": "ffffff"
    }
  },
  "away": {
    "players": [
      {
        "player": {
          "name": "Cássio",
          "firstName": "",
          "lastName": "",
          "slug": "cassio",
          "shortName": "Cássio",
          "position": "G",
          "jerseyNumber": "12",
          "userCount": 2555,
          "id": 27756,
          "country": {
            "alpha2": "BR",
            "name": "Brazil"
          },
          "marketValueCurrency": "EUR",
          "dateOfBirthTimestamp": 549936000
        },
        "shirtNumber": 12,
        "jerseyNumber": "12",
        "position": "G",
        "substitute": false,
        "captain": true,
        "statistics": {
          "totalPass": 23,
          "accuratePass": 13,
          "totalLongBalls": 12,
          "accurateLongBalls": 2,
          "goodHighClaim": 2,
          "savedShotsFromInsideTheBox": 2,
          "saves": 3,
          "minutesPlayed": 90,
          "touches": 33,
          "rating": 7.4,
          "possessionLostCtrl": 10,
          "penaltyShootoutSave": 1
        }
      },
      {
        "player": {
          "name": "Fagner",
          "firstName": "",
          "lastName": "",
          "slug": "fagner",
          "shortName": "Fagner",
          "position": "D",
          "jerseyNumber": "23",
          "userCount": 1756,
          "id": 25554,
          "country": {
            "alpha2": "BR",
            "name": "Brazil"
          },
          "marketValueCurrency": "EUR",
          "dateOfBirthTimestamp": 613526400
        },
        "shirtNumber": 23,
        "jerseyNumber": "23",
        "position": "D",
        "substitute": false,
        "statistics": {
          "totalPass": 36,
          "accuratePass": 30,
          "totalLongBalls": 2,
          "accurateLongBalls": 1,
          "totalCross": 3,
          "aerialLost": 1,
          "duelLost": 8,
          "duelWon": 3,
          "challengeLost": 2,
          "totalContest": 2,
          "blockedScoringAttempt": 1,
          "totalClearance": 3,
          "totalTackle": 1,
          "wasFouled": 2,
          "fouls": 3,
          "minutesPlayed": 70,
          "touches": 63,
          "rating": 6.1,
          "possessionLostCtrl": 13
        }
      },
      {
        "player": {
          "name": "Gil",
          "firstName": "",
          "lastName": "",
          "slug": "gil",
          "shortName": "Gil",
          "position": "D",
          "jerseyNumber": "4",
          "userCount": 1046,
          "id": 106402,
          "country": {
            "alpha2": "BR",
            "name": "Brazil"
          },
          "marketValueCurrency": "EUR",
          "dateOfBirthTimestamp": 550454400,
          "fieldTranslations": {
            "nameTranslation": {
              "ar": "جيل"
            },
            "shortNameTranslation": {}
          }
        },
        "shirtNumber": 4,
        "jerseyNumber": "4",
        "position": "D",
        "substitute": false,
        "statistics": {
          "totalPass": 65,
          "accuratePass": 61,
          "totalLongBalls": 5,
          "accurateLongBalls": 2,
          "aerialLost": 5,
          "aerialWon": 1,
          "duelLost": 6,
          "duelWon": 2,
          "totalClearance": 1,
          "interceptionWon": 1,
          "totalTackle": 1,
          "fouls": 1,
          "minutesPlayed": 90,
          "touches": 70,
          "rating": 6.5,
          "possessionLostCtrl": 4
        }
      },
      {
        "player": {
          "name": "Danilo Avelar",
          "firstName": "",
          "lastName": "",
          "slug": "danilo-avelar",
          "shortName": "Danilo Avelar",
          "position": "D",
          "jerseyNumber": "22",
          "userCount": 207,
          "id": 121221,
          "country": {
            "alpha2": "BR",
            "name": "Brazil"
          },
          "marketValueCurrency": "EUR",
          "dateOfBirthTimestamp": 613353600
        },
        "shirtNumber": 35,
        "jerseyNumber": "35",
        "position": "D",
        "substitute": false,
        "statistics": {
          "totalPass": 60,
          "accuratePass": 56,
          "totalLongBalls": 4,
          "accurateLongBalls": 2,
          "aerialLost": 3,
          "aerialWon": 4,
          "duelLost": 4,
          "duelWon": 5,
          "dispossessed": 1,
          "totalClearance": 6,
          "outfielderBlock": 1,
          "interceptionWon": 2,
          "wasFouled": 2,
          "fouls": 1,
          "minutesPlayed": 90,
          "touches": 73,
          "rating": 7.2,
          "possessionLostCtrl": 5,
          "penaltyShootoutGoal": 1
        }
      },
      {
        "player": {
          "name": "Carlos Augusto",
          "firstName": "",
          "lastName": "",
          "slug": "carlos-augusto",
          "shortName": "C. Augusto",
          "position": "M",
          "jerseyNumber": "30",
          "userCount": 2493,
          "id": 929199,
          "country": {
            "alpha2": "BR",
            "name": "Brazil"
          },
          "marketValueCurrency": "EUR",
          "dateOfBirthTimestamp": 915667200,
          "fieldTranslations": {
            "nameTranslation": {
              "ar": "أوغوستو, كارلوس"
            },
            "shortNameTranslation": {}
          }
        },
        "shirtNumber": 30,
        "jerseyNumber": "30",
        "position": "D",
        "substitute": false,
        "statistics": {
          "totalPass": 27,
          "accuratePass": 23,
          "totalLongBalls": 3,
          "accurateLongBalls": 1,
          "totalCross": 2,
          "accurateCross": 1,
          "aerialWon": 2,
          "duelWon": 3,
          "totalClearance": 2,
          "outfielderBlock": 1,
          "interceptionWon": 1,
          "wasFouled": 1,
          "minutesPlayed": 82,
          "touches": 41,
          "rating": 6.9,
          "possessionLostCtrl": 7,
          "keyPass": 1
        }
      },
      {
        "player": {
          "name": "Gabriel",
          "firstName": "",
          "lastName": "",
          "slug": "gabriel",
          "shortName": "Gabriel",
          "position": "M",
          "jerseyNumber": "23",
          "userCount": 421,
          "id": 242052,
          "country": {
            "alpha2": "BR",
            "name": "Brazil"
          },
          "marketValueCurrency": "EUR",
          "dateOfBirthTimestamp": 710726400
        },
        "shirtNumber": 5,
        "jerseyNumber": "5",
        "position": "M",
        "substitute": false,
        "statistics": {
          "totalPass": 50,
          "accuratePass": 45,
          "totalLongBalls": 5,
          "accurateLongBalls": 3,
          "totalCross": 1,
          "aerialWon": 1,
          "duelLost": 1,
          "duelWon": 3,
          "challengeLost": 1,
          "totalClearance": 3,
          "interceptionWon": 1,
          "totalTackle": 2,
          "minutesPlayed": 59,
          "touches": 60,
          "rating": 6.9,
          "possessionLostCtrl": 6,
          "keyPass": 1
        }
      },
      {
        "player": {
          "name": "Éderson",
          "firstName": "",
          "lastName": "",
          "slug": "ederson",
          "shortName": "Éderson",
          "position": "M",
          "jerseyNumber": "13",
          "userCount": 2156,
          "id": 946888,
          "country": {
            "alpha2": "BR",
            "name": "Brazil"
          },
          "marketValueCurrency": "EUR",
          "dateOfBirthTimestamp": 931305600,
          "fieldTranslations": {
            "nameTranslation": {
              "ar": "إيدرسون"
            },
            "shortNameTranslation": {}
          }
        },
        "shirtNumber": 15,
        "jerseyNumber": "15",
        "position": "M",
        "substitute": false,
        "statistics": {
          "totalPass": 51,
          "accuratePass": 45,
          "totalLongBalls": 5,
          "accurateLongBalls": 2,
          "aerialLost": 1,
          "aerialWon": 1,
          "duelLost": 6,
          "duelWon": 11,
          "challengeLost": 1,
          "dispossessed": 2,
          "totalContest": 3,
          "wonContest": 1,
          "blockedScoringAttempt": 1,
          "totalTackle": 5,
          "wasFouled": 4,
          "minutesPlayed": 90,
          "touches": 68,
          "rating": 6.7,
          "possessionLostCtrl": 11
        }
      },
      {
        "player": {
          "name": "Ramiro",
          "firstName": "",
          "lastName": "",
          "slug": "ramiro",
          "shortName": "Ramiro",
          "position": "M",
          "jerseyNumber": "17",
          "userCount": 307,
          "id": 330693,
          "country": {
            "alpha2": "BR",
            "name": "Brazil"
          },
          "marketValueCurrency": "EUR",
          "dateOfBirthTimestamp": 738028800
        },
        "shirtNumber": 8,
        "jerseyNumber": "8",
        "position": "M",
        "substitute": false,
        "statistics": {
          "totalPass": 28,
          "accuratePass": 24,
          "totalLongBalls": 2,
          "accurateLongBalls": 1,
          "aerialLost": 1,
          "aerialWon": 1,
          "duelLost": 5,
          "duelWon": 2,
          "challengeLost": 1,
          "dispossessed": 1,
          "onTargetScoringAttempt": 1,
          "totalClearance": 2,
          "wasFouled": 1,
          "fouls": 2,
          "minutesPlayed": 59,
          "touches": 38,
          "rating": 6.4,
          "possessionLostCtrl": 8
        }
      },
      {
        "player": {
          "name": "Luan",
          "firstName": "",
          "lastName": "",
          "slug": "luan",
          "shortName": "Luan",
          "position": "F",
          "userCount": 1398,
          "id": 386210,
          "country": {
            "alpha2": "BR",
            "name": "Brazil"
          },
          "marketValueCurrency": "EUR",
          "dateOfBirthTimestamp": 733190400,
          "fieldTranslations": {
            "nameTranslation": {
              "ar": "لوان"
            },
            "shortNameTranslation": {}
          }
        },
        "shirtNumber": 7,
        "jerseyNumber": "7",
        "position": "M",
        "substitute": false,
        "statistics": {
          "totalPass": 44,
          "accuratePass": 34,
          "totalLongBalls": 4,
          "accurateLongBalls": 2,
          "totalCross": 7,
          "accurateCross": 2,
          "aerialLost": 3,
          "duelLost": 5,
          "duelWon": 4,
          "dispossessed": 1,
          "totalContest": 1,
          "blockedScoringAttempt": 1,
          "totalClearance": 1,
          "interceptionWon": 1,
          "wasFouled": 4,
          "minutesPlayed": 90,
          "touches": 65,
          "rating": 7.3,
          "possessionLostCtrl": 20,
          "keyPass": 6
        }
      },
      {
        "player": {
          "name": "Mateus Vital",
          "firstName": "",
          "lastName": "",
          "slug": "mateus-vital",
          "shortName": "Mateus Vital",
          "position": "M",
          "jerseyNumber": "7",
          "userCount": 668,
          "id": 823653,
          "country": {
            "alpha2": "BR",
            "name": "Brazil"
          },
          "marketValueCurrency": "EUR",
          "dateOfBirthTimestamp": 887241600
        },
        "shirtNumber": 22,
        "jerseyNumber": "22",
        "position": "M",
        "substitute": false,
        "statistics": {
          "totalPass": 9,
          "accuratePass": 8,
          "totalCross": 1,
          "aerialLost": 3,
          "aerialWon": 1,
          "duelLost": 4,
          "duelWon": 2,
          "dispossessed": 1,
          "shotOffTarget": 1,
          "blockedScoringAttempt": 2,
          "totalTackle": 1,
          "minutesPlayed": 45,
          "touches": 20,
          "rating": 6.6,
          "possessionLostCtrl": 5
        }
      },
      {
        "player": {
          "name": "Jô",
          "firstName": "",
          "lastName": "",
          "slug": "jo",
          "shortName": "Jô",
          "position": "F",
          "userCount": 565,
          "id": 17878,
          "country": {
            "alpha2": "BR",
            "name": "Brazil"
          },
          "marketValueCurrency": "EUR",
          "dateOfBirthTimestamp": 543196800
        },
        "shirtNumber": 77,
        "jerseyNumber": "77",
        "position": "F",
        "substitute": false,
        "statistics": {
          "totalPass": 17,
          "accuratePass": 16,
          "totalLongBalls": 1,
          "accurateLongBalls": 1,
          "aerialLost": 5,
          "aerialWon": 2,
          "duelLost": 6,
          "duelWon": 5,
          "totalContest": 2,
          "wonContest": 1,
          "shotOffTarget": 2,
          "onTargetScoringAttempt": 2,
          "goals": 1,
          "totalClearance": 1,
          "wasFouled": 2,
          "fouls": 2,
          "penaltyWon": 1,
          "totalOffside": 1,
          "minutesPlayed": 90,
          "touches": 29,
          "rating": 7.9,
          "possessionLostCtrl": 5,
          "penaltyShootoutGoal": 1
        }
      },
      {
        "player": {
          "name": "Everaldo",
          "firstName": "",
          "lastName": "",
          "slug": "everaldo",
          "shortName": "Everaldo",
          "position": "M",
          "userCount": 176,
          "id": 923951,
          "country": {
            "alpha2": "BR",
            "name": "Brazil"
          },
          "marketValueCurrency": "EUR",
          "dateOfBirthTimestamp": 770083200
        },
        "shirtNumber": 37,
        "jerseyNumber": "37",
        "position": "M",
        "substitute": true,
        "statistics": {
          "totalPass": 6,
          "accuratePass": 5,
          "totalLongBalls": 1,
          "aerialLost": 2,
          "duelLost": 4,
          "duelWon": 2,
          "dispossessed": 1,
          "totalTackle": 2,
          "fouls": 1,
          "minutesPlayed": 45,
          "touches": 13,
          "rating": 6.5,
          "possessionLostCtrl": 3
        }
      },
      {
        "player": {
          "name": "Victor Cantillo",
          "firstName": "",
          "lastName": "",
          "slug": "victor-cantillo",
          "shortName": "Victor Cantillo",
          "position": "M",
          "jerseyNumber": "24",
          "userCount": 899,
          "id": 355802,
          "country": {
            "alpha2": "CO",
            "name": "Colombia"
          },
          "marketValueCurrency": "EUR",
          "dateOfBirthTimestamp": 750643200
        },
        "shirtNumber": 24,
        "jerseyNumber": "24",
        "position": "M",
        "substitute": true,
        "statistics": {
          "totalPass": 26,
          "accuratePass": 23,
          "totalLongBalls": 4,
          "accurateLongBalls": 4,
          "aerialWon": 1,
          "duelWon": 2,
          "shotOffTarget": 1,
          "wasFouled": 1,
          "minutesPlayed": 31,
          "touches": 28,
          "rating": 6.5,
          "possessionLostCtrl": 3,
          "penaltyShootoutMiss": 1
        }
      },
      {
        "player": {
          "name": "Ángelo Araos",
          "firstName": "",
          "lastName": "",
          "slug": "angelo-araos",
          "shortName": "Á. Araos",
          "position": "M",
          "jerseyNumber": "32",
          "userCount": 504,
          "id": 819085,
          "country": {
            "alpha2": "CL",
            "name": "Chile"
          },
          "marketValueCurrency": "EUR",
          "dateOfBirthTimestamp": 852508800
        },
        "shirtNumber": 21,
        "jerseyNumber": "21",
        "position": "M",
        "substitute": true,
        "statistics": {
          "totalPass": 12,
          "accuratePass": 9,
          "totalLongBalls": 1,
          "accurateLongBalls": 1,
          "totalCross": 2,
          "aerialLost": 1,
          "duelLost": 2,
          "fouls": 1,
          "minutesPlayed": 31,
          "touches": 18,
          "rating": 6.6,
          "possessionLostCtrl": 9,
          "keyPass": 1
        }
      },
      {
        "player": {
          "name": "Michel Macedo",
          "firstName": "",
          "lastName": "",
          "slug": "michel-macedo",
          "shortName": "M. Macedo",
          "position": "D",
          "userCount": 90,
          "id": 42564,
          "country": {
            "alpha2": "BR",
            "name": "Brazil"
          },
          "marketValueCurrency": "EUR",
          "dateOfBirthTimestamp": 635040000
        },
        "shirtNumber": 2,
        "jerseyNumber": "2",
        "position": "D",
        "substitute": true,
        "statistics": {
          "totalPass": 9,
          "accuratePass": 7,
          "totalLongBalls": 1,
          "accurateLongBalls": 1,
          "duelLost": 1,
          "duelWon": 1,
          "challengeLost": 1,
          "shotOffTarget": 1,
          "outfielderBlock": 1,
          "interceptionWon": 2,
          "wasFouled": 1,
          "minutesPlayed": 20,
          "touches": 18,
          "rating": 6.5,
          "possessionLostCtrl": 3,
          "penaltyShootoutMiss": 1
        }
      },
      {
        "player": {
          "name": "Sidcley",
          "firstName": "",
          "lastName": "",
          "slug": "sidcley",
          "shortName": "Sidcley",
          "position": "D",
          "jerseyNumber": "16",
          "userCount": 112,
          "id": 592086,
          "country": {
            "alpha2": "BR",
            "name": "Brazil"
          },
          "marketValueCurrency": "EUR",
          "dateOfBirthTimestamp": 737251200,
          "fieldTranslations": {
            "nameTranslation": {
              "ar": "سيدكلي"
            },
            "shortNameTranslation": {}
          }
        },
        "shirtNumber": 16,
        "jerseyNumber": "16",
        "position": "D",
        "substitute": true,
        "statistics": {
          "totalPass": 3,
          "accuratePass": 2,
          "totalCross": 2,
          "accurateCross": 1,
          "aerialLost": 1,
          "duelLost": 1,
          "minutesPlayed": 8,
          "touches": 9,
          "rating": 6.9,
          "possessionLostCtrl": 2,
          "penaltyShootoutGoal": 1
        }
      },
      {
        "player": {
          "name": "Walter",
          "slug": "walter",
          "shortName": "Walter",
          "position": "G",
          "jerseyNumber": "1",
          "userCount": 271,
          "id": 329055,
          "country": {
            "alpha2": "BR",
            "name": "Brazil"
          },
          "marketValueCurrency": "EUR",
          "dateOfBirthTimestamp": 564192000,
          "fieldTranslations": {
            "nameTranslation": {
              "ar": "والتر"
            },
            "shortNameTranslation": {}
          }
        },
        "shirtNumber": 27,
        "jerseyNumber": "27",
        "position": "G",
        "substitute": true,
        "statistics": {}
      },
      {
        "player": {
          "name": "Bruno Méndez",
          "firstName": "",
          "lastName": "",
          "slug": "bruno-mendez",
          "shortName": "Bruno Méndez",
          "position": "D",
          "jerseyNumber": "2",
          "userCount": 1123,
          "id": 923000,
          "country": {
            "alpha2": "UY",
            "name": "Uruguay"
          },
          "marketValueCurrency": "EUR",
          "dateOfBirthTimestamp": 936921600
        },
        "shirtNumber": 14,
        "jerseyNumber": "14",
        "position": "D",
        "substitute": true,
        "statistics": {}
      },
      {
        "player": {
          "name": "Lucas Piton",
          "slug": "lucas-piton",
          "shortName": "Lucas Piton",
          "position": "D",
          "jerseyNumber": "6",
          "userCount": 891,
          "id": 982174,
          "country": {
            "alpha2": "BR",
            "name": "Brazil"
          },
          "marketValueCurrency": "EUR",
          "dateOfBirthTimestamp": 971049600
        },
        "shirtNumber": 6,
        "jerseyNumber": "6",
        "position": "D",
        "substitute": true,
        "statistics": {}
      },
      {
        "player": {
          "name": "Guilherme Camacho",
          "slug": "guilherme-camacho",
          "shortName": "G. Camacho",
          "position": "M",
          "userCount": 234,
          "id": 76444,
          "country": {
            "alpha2": "BR",
            "name": "Brazil"
          },
          "marketValueCurrency": "EUR",
          "dateOfBirthTimestamp": 636336000
        },
        "shirtNumber": 20,
        "jerseyNumber": "20",
        "position": "M",
        "substitute": true,
        "statistics": {}
      },
      {
        "player": {
          "name": "Roni",
          "firstName": "Roni",
          "lastName": "",
          "slug": "roni",
          "shortName": "Roni",
          "position": "M",
          "jerseyNumber": "29",
          "userCount": 582,
          "id": 1046440,
          "country": {
            "alpha2": "BR",
            "name": "Brazil"
          },
          "marketValueCurrency": "EUR",
          "dateOfBirthTimestamp": 924134400
        },
        "shirtNumber": 29,
        "jerseyNumber": "29",
        "position": "M",
        "substitute": true,
        "statistics": {}
      },
      {
        "player": {
          "name": "Léo Natel",
          "slug": "leo-natel",
          "shortName": "L. Natel",
          "position": "M",
          "jerseyNumber": "11",
          "userCount": 212,
          "id": 875905,
          "country": {
            "alpha2": "BR",
            "name": "Brazil"
          },
          "marketValueCurrency": "EUR",
          "dateOfBirthTimestamp": 858297600
        },
        "shirtNumber": 18,
        "jerseyNumber": "18",
        "position": "M",
        "substitute": true,
        "statistics": {}
      },
      {
        "player": {
          "name": "Janderson",
          "slug": "janderson",
          "shortName": "Janderson",
          "position": "F",
          "jerseyNumber": "77",
          "userCount": 174,
          "id": 870898,
          "country": {
            "alpha2": "BR",
            "name": "Brazil"
          },
          "marketValueCurrency": "EUR",
          "dateOfBirthTimestamp": 919987200
        },
        "shirtNumber": 31,
        "jerseyNumber": "31",
        "position": "M",
        "substitute": true,
        "statistics": {}
      }
    ],
    "supportStaff": [],
    "formation": "4-2-3-1",
    "playerColor": {
      "primary": "000000",
      "number": "ffffff",
      "outline": "000000",
      "fancyNumber": "ffffff"
    },
    "goalkeeperColor": {
      "primary": "cc0033",
      "number": "000000",
      "outline": "cc0033",
      "fancyNumber": "ffffff"
    }
  }
}