{
  "confirmed": true,
  "home": {
    "players": [
      {
        "player": {
          "name": "Douglas Friedrich",
          "firstName": "",
          "lastName": "",
          "slug": "douglas-friedrich",
          "shortName": "D. Friedrich",
          "position": "G",
          "jerseyNumber": "22",
          "userCount": 189,
          "id": 838439,
          "country": {
            "alpha2": "BR",
            "name": "Brazil"
          },
          "marketValueCurrency": "EUR",
          "dateOfBirthTimestamp": 597888000,
          "fieldTranslations": {
            "nameTranslation": {
              "ar": "فريدريش, دوغلاس"
            },
            "shortNameTranslation": {}
          }
        },
        "shirtNumber": 1,
        "jerseyNumber": "1",
        "position": "G",
        "substitute": false,
        "statistics": {
          "totalPass": 29,
          "accuratePass": 24,
          "totalLongBalls": 18,
          "accurateLongBalls": 13,
          "totalClearance": 2,
          "interceptionWon": 1,
          "goodHighClaim": 1,
          "savedShotsFromInsideTheBox": 1,
          "saves": 4,
          "punches": 1,
          "totalKeeperSweeper": 1,
          "accurateKeeperSweeper": 1,
          "minutesPlayed": 90,
          "touches": 46,
          "rating": 7.2,
          "possessionLostCtrl": 6
        }
      },
      {
        "player": {
          "name": "João Pedro",
          "firstName": "",
          "lastName": "",
          "slug": "joao-pedro",
          "shortName": "João Pedro",
          "position": "D",
          "jerseyNumber": "18",
          "userCount": 372,
          "id": 605528,
          "country": {
            "alpha2": "BR",
            "name": "Brazil"
          },
          "marketValueCurrency": "EUR",
          "dateOfBirthTimestamp": 848016000
        },
        "shirtNumber": 23,
        "jerseyNumber": "23",
        "position": "D",
        "substitute": false,
        "statistics": {
          "totalPass": 39,
          "accuratePass": 32,
          "totalLongBalls": 1,
          "totalCross": 4,
          "accurateCross": 1,
          "aerialLost": 2,
          "aerialWon": 1,
          "duelLost": 5,
          "duelWon": 6,
          "dispossessed": 1,
          "blockedScoringAttempt": 1,
          "totalClearance": 1,
          "interceptionWon": 1,
          "totalTackle": 4,
          "wasFouled": 1,
          "fouls": 3,
          "minutesPlayed": 90,
          "touches": 63,
          "rating": 7.2,
          "possessionLostCtrl": 14,
          "keyPass": 5
        }
      },
      {
        "player": {
          "name": "Lucas Fonseca",
          "slug": "lucas-fonseca",
          "shortName": "L. Fonseca",
          "position": "D",
          "userCount": 55,
          "id": 243441,
          "country": {
            "alpha2": "BR",
            "name": "Brazil"
          },
          "marketValueCurrency": "EUR",
          "dateOfBirthTimestamp": 491788800
        },
        "shirtNumber": 28,
        "jerseyNumber": "28",
        "position": "D",
        "substitute": false,
        "captain": true,
        "statistics": {
          "totalPass": 27,
          "accuratePass": 19,
          "totalLongBalls": 3,
          "accurateLongBalls": 1,
          "aerialLost": 1,
          "aerialWon": 1,
          "duelLost": 1,
          "duelWon": 3,
          "totalClearance": 3,
          "outfielderBlock": 1,
          "interceptionWon": 1,
          "totalTackle": 1,
          "wasFouled": 1,
          "minutesPlayed": 90,
          "touches": 34,
          "rating": 6.8,
          "possessionLostCtrl": 8
        }
      },
      {
        "player": {
          "name": "Wanderson",
          "firstName": "",
          "lastName": "",
          "slug": "wanderson",
          "shortName": "Wanderson",
          "position": "D",
          "jerseyNumber": "4",
          "userCount": 45,
          "id": 368846,
          "country": {
            "alpha2": "BR",
            "name": "Brazil"
          },
          "marketValueCurrency": "EUR",
          "dateOfBirthTimestamp": 665884800
        },
        "shirtNumber": 3,
        "jerseyNumber": "3",
        "position": "D",
        "substitute": false,
        "statistics": {
          "totalPass": 42,
          "accuratePass": 39,
          "totalLongBalls": 7,
          "accurateLongBalls": 5,
          "totalClearance": 6,
          "outfielderBlock": 1,
          "minutesPlayed": 90,
          "touches": 49,
          "rating": 6.9,
          "possessionLostCtrl": 3
        }
      },
      {
        "player": {
          "name": "Moisés",
          "firstName": "",
          "lastName": "",
          "slug": "moises",
          "shortName": "Moisés",
          "position": "D",
          "jerseyNumber": "27",
          "userCount": 227,
          "id": 840158,
          "country": {
            "alpha2": "BR",
            "name": "Brazil"
          },
          "marketValueCurrency": "EUR",
          "dateOfBirthTimestamp": 794880000
        },
        "shirtNumber": 6,
        "jerseyNumber": "6",
        "position": "D",
        "substitute": false,
        "statistics": {
          "totalPass": 34,
          "accuratePass": 31,
          "totalLongBalls": 1,
          "totalCross": 7,
          "aerialLost": 1,
          "aerialWon": 1,
          "duelLost": 6,
          "duelWon": 4,
          "dispossessed": 3,
          "totalContest": 1,
          "wonContest": 1,
          "shotOffTarget": 1,
          "totalClearance": 6,
          "totalTackle": 2,
          "fouls": 2,
          "minutesPlayed": 90,
          "touches": 65,
          "rating": 6.6,
          "possessionLostCtrl": 14
        }
      },
      {
        "player": {
          "name": "Flávio",
          "slug": "flavio",
          "shortName": "Flávio",
          "position": "M",
          "jerseyNumber": "24",
          "userCount": 208,
          "id": 839521,
          "country": {
            "alpha2": "BR",
            "name": "Brazil"
          },
          "marketValueCurrency": "EUR",
          "dateOfBirthTimestamp": 823910400,
          "fieldTranslations": {
            "nameTranslation": {
              "ar": "فلافيو"
            },
            "shortNameTranslation": {}
          }
        },
        "shirtNumber": 5,
        "jerseyNumber": "5",
        "position": "M",
        "substitute": false,
        "statistics": {
          "totalPass": 40,
          "accuratePass": 34,
          "totalLongBalls": 3,
          "accurateLongBalls": 2,
          "totalCross": 2,
          "accurateCross": 1,
          "aerialLost": 1,
          "aerialWon": 3,
          "duelLost": 6,
          "duelWon": 6,
          "challengeLost": 2,
          "dispossessed": 1,
          "totalContest": 1,
          "wonContest": 1,
          "totalTackle": 2,
          "wasFouled": 1,
          "fouls": 2,
          "minutesPlayed": 79,
          "touches": 50,
          "rating": 6.7,
          "possessionLostCtrl": 8,
          "keyPass": 1
        }
      },
      {
        "player": {
          "name": "Gregore",
          "slug": "gregore",
          "shortName": "Gregore",
          "position": "M",
          "jerseyNumber": "26",
          "userCount": 349,
          "id": 840276,
          "country": {
            "alpha2": "BR",
            "name": "Brazil"
          },
          "marketValueCurrency": "EUR",
          "dateOfBirthTimestamp": 762566400,
          "fieldTranslations": {
            "nameTranslation": {
              "ar": "غريغور"
            },
            "shortNameTranslation": {}
          }
        },
        "shirtNumber": 26,
        "jerseyNumber": "26",
        "position": "M",
        "substitute": false,
        "statistics": {
          "totalPass": 63,
          "accuratePass": 60,
          "totalLongBalls": 3,
          "accurateLongBalls": 3,
          "aerialWon": 2,
          "duelLost": 7,
          "duelWon": 5,
          "challengeLost": 2,
          "bigChanceCreated": 1,
          "shotOffTarget": 1,
          "blockedScoringAttempt": 1,
          "totalClearance": 1,
          "outfielderBlock": 1,
          "interceptionWon": 1,
          "lastManTackle": 1,
          "totalTackle": 2,
          "wasFouled": 1,
          "fouls": 5,
          "minutesPlayed": 90,
          "touches": 73,
          "rating": 7.1,
          "possessionLostCtrl": 4,
          "keyPass": 1
        }
      },
      {
        "player": {
          "name": "Ronaldo",
          "firstName": "",
          "lastName": "",
          "slug": "ronaldo",
          "shortName": "Ronaldo",
          "position": "M",
          "jerseyNumber": "41",
          "userCount": 166,
          "id": 824152,
          "country": {
            "alpha2": "BR",
            "name": "Brazil"
          },
          "marketValueCurrency": "EUR",
          "dateOfBirthTimestamp": 846028800
        },
        "shirtNumber": 16,
        "jerseyNumber": "16",
        "position": "M",
        "substitute": false,
        "statistics": {
          "totalPass": 42,
          "accuratePass": 37,
          "totalLongBalls": 5,
          "accurateLongBalls": 4,
          "aerialWon": 1,
          "duelLost": 7,
          "duelWon": 6,
          "challengeLost": 3,
          "dispossessed": 1,
          "totalContest": 1,
          "wonContest": 1,
          "totalClearance": 3,
          "outfielderBlock": 1,
          "interceptionWon": 2,
          "totalTackle": 2,
          "wasFouled": 2,
          "fouls": 3,
          "totalOffside": 1,
          "minutesPlayed": 90,
          "touches": 57,
          "rating": 7,
          "possessionLostCtrl": 7,
          "keyPass": 1
        }
      },
      {
        "player": {
          "name": "Élber",
          "firstName": "",
          "lastName": "",
          "slug": "elber",
          "shortName": "Élber",
          "position": "M",
          "jerseyNumber": "7",
          "userCount": 338,
          "id": 243413,
          "country": {
            "alpha2": "BR",
            "name": "Brazil"
          },
          "marketValueCurrency": "EUR",
          "dateOfBirthTimestamp": 706924800
        },
        "shirtNumber": 7,
        "jerseyNumber": "7",
        "position": "F",
        "substitute": false,
        "statistics": {
          "totalPass": 17,
          "accuratePass": 16,
          "aerialLost": 1,
          "duelLost": 2,
          "duelWon": 7,
          "totalContest": 3,
          "wonContest": 3,
          "bigChanceCreated": 1,
          "bigChanceMissed": 1,
          "onTargetScoringAttempt": 1,
          "blockedScoringAttempt": 1,
          "wasFouled": 4,
          "fouls": 1,
          "minutesPlayed": 62,
          "touches": 29,
          "rating": 7.3,
          "possessionLostCtrl": 2,
          "keyPass": 2
        }
      },
      {
        "player": {
          "name": "Gilberto",
          "firstName": "",
          "lastName": "",
          "slug": "gilberto",
          "shortName": "Gilberto",
          "position": "F",
          "userCount": 833,
          "id": 158561,
          "country": {
            "alpha2": "BR",
            "name": "Brazil"
          },
          "marketValueCurrency": "EUR",
          "dateOfBirthTimestamp": 613008000
        },
        "shirtNumber": 9,
        "jerseyNumber": "9",
        "position": "F",
        "substitute": false,
        "statistics": {
          "totalPass": 19,
          "accuratePass": 13,
          "totalLongBalls": 2,
          "accurateLongBalls": 1,
          "aerialLost": 2,
          "duelLost": 3,
          "duelWon": 3,
          "dispossessed": 1,
          "bigChanceMissed": 1,
          "onTargetScoringAttempt": 1,
          "totalTackle": 1,
          "wasFouled": 2,
          "minutesPlayed": 59,
          "touches": 29,
          "rating": 6.5,
          "possessionLostCtrl": 9,
          "keyPass": 1
        }
      },
      {
        "player": {
          "name": "Arthur Caíke",
          "slug": "arthur-caike",
          "shortName": "Arthur",
          "position": "M",
          "jerseyNumber": "17",
          "userCount": 110,
          "id": 829832,
          "country": {
            "alpha2": "BR",
            "name": "Brazil"
          },
          "marketValueCurrency": "EUR",
          "dateOfBirthTimestamp": 708566400
        },
        "shirtNumber": 77,
        "jerseyNumber": "77",
        "position": "F",
        "substitute": false,
        "statistics": {
          "totalPass": 21,
          "accuratePass": 13,
          "totalLongBalls": 2,
          "accurateLongBalls": 1,
          "totalCross": 2,
          "accurateCross": 1,
          "aerialWon": 4,
          "duelLost": 5,
          "duelWon": 7,
          "dispossessed": 4,
          "totalContest": 2,
          "wonContest": 2,
          "shotOffTarget": 1,
          "onTargetScoringAttempt": 3,
          "blockedScoringAttempt": 2,
          "goals": 1,
          "totalClearance": 2,
          "totalTackle": 1,
          "fouls": 1,
          "minutesPlayed": 90,
          "touches": 44,
          "rating": 7.8,
          "possessionLostCtrl": 16,
          "keyPass": 1
        }
      },
      {
        "player": {
          "name": "Fernandão",
          "firstName": "",
          "lastName": "",
          "slug": "fernandao",
          "shortName": "Fernandão",
          "position": "F",
          "jerseyNumber": "9",
          "userCount": 171,
          "id": 329251,
          "country": {
            "alpha2": "BR",
            "name": "Brazil"
          },
          "marketValueCurrency": "EUR",
          "dateOfBirthTimestamp": 543801600
        },
        "shirtNumber": 20,
        "jerseyNumber": "20",
        "position": "F",
        "substitute": true,
        "statistics": {
          "totalPass": 12,
          "accuratePass": 8,
          "totalLongBalls": 1,
          "accurateLongBalls": 1,
          "aerialLost": 1,
          "aerialWon": 3,
          "duelLost": 1,
          "duelWon": 4,
          "totalContest": 1,
          "wonContest": 1,
          "shotOffTarget": 1,
          "minutesPlayed": 31,
          "touches": 15,
          "rating": 6.7,
          "possessionLostCtrl": 4
        }
      },
      {
        "player": {
          "name": "Lucca",
          "firstName": "",
          "lastName": "",
          "slug": "lucca",
          "shortName": "Lucca",
          "position": "F",
          "jerseyNumber": "30",
          "userCount": 189,
          "id": 329235,
          "country": {
            "alpha2": "BR",
            "name": "Brazil"
          },
          "marketValueCurrency": "EUR",
          "dateOfBirthTimestamp": 634953600
        },
        "shirtNumber": 11,
        "jerseyNumber": "11",
        "position": "M",
        "substitute": true,
        "statistics": {
          "totalPass": 13,
          "accuratePass": 12,
          "totalCross": 2,
          "aerialLost": 1,
          "duelLost": 2,
          "duelWon": 3,
          "totalContest": 2,
          "wonContest": 1,
          "shotOffTarget": 1,
          "wasFouled": 2,
          "minutesPlayed": 28,
          "touches": 21,
          "rating": 6.7,
          "possessionLostCtrl": 4
        }
      },
      {
        "player": {
          "name": "Shaylon",
          "slug": "shaylon",
          "shortName": "Shaylon",
          "position": "M",
          "userCount": 193,
          "id": 874723,
          "country": {
            "alpha2": "BR",
            "name": "Brazil"
          },
          "marketValueCurrency": "EUR",
          "dateOfBirthTimestamp": 862099200
        },
        "shirtNumber": 27,
        "jerseyNumber": "27",
        "position": "M",
        "substitute": true,
        "statistics": {
          "totalPass": 6,
          "accuratePass": 5,
          "duelLost": 2,
          "challengeLost": 1,
          "dispossessed": 1,
          "minutesPlayed": 11,
          "touches": 9,
          "rating": 6.2,
          "possessionLostCtrl": 4
        }
      },
      {
        "player": {
          "name": "Anderson",
          "slug": "anderson",
          "shortName": "Anderson",
          "position": "G",
          "jerseyNumber": "33",
          "userCount": 19,
          "id": 791193,
          "country": {
            "alpha2": "BR",
            "name": "Brazil"
          },
          "marketValueCurrency": "EUR",
          "dateOfBirthTimestamp": 438134400
        },
        "shirtNumber": 33,
        "jerseyNumber": "33",
        "position": "G",
        "substitute": true,
        "statistics": {}
      },
      {
        "player": {
          "name": "Nino Paraíba",
          "slug": "nino-paraiba",
          "shortName": "N. Paraíba",
          "position": "D",
          "userCount": 157,
          "id": 77375,
          "country": {
            "alpha2": "BR",
            "name": "Brazil"
          },
          "marketValueCurrency": "EUR",
          "dateOfBirthTimestamp": 505699200
        },
        "shirtNumber": 2,
        "jerseyNumber": "2",
        "position": "D",
        "substitute": true,
        "statistics": {}
      },
      {
        "player": {
          "name": "Ernando",
          "slug": "ernando",
          "shortName": "Ernando",
          "position": "D",
          "jerseyNumber": "14",
          "userCount": 32,
          "id": 82967,
          "country": {
            "alpha2": "BR",
            "name": "Brazil"
          },
          "marketValueCurrency": "EUR",
          "dateOfBirthTimestamp": 584841600
        },
        "shirtNumber": 14,
        "jerseyNumber": "14",
        "position": "D",
        "substitute": true,
        "statistics": {}
      },
      {
        "player": {
          "name": "Ignácio",
          "firstName": "",
          "lastName": "",
          "slug": "ignacio",
          "shortName": "Ignácio",
          "position": "D",
          "jerseyNumber": "14",
          "userCount": 214,
          "id": 958382,
          "country": {
            "alpha2": "BR",
            "name": "Brazil"
          },
          "marketValueCurrency": "EUR",
          "dateOfBirthTimestamp": 849398400
        },
        "shirtNumber": 34,
        "jerseyNumber": "34",
        "position": "D",
        "substitute": true,
        "statistics": {}
      },
      {
        "player": {
          "name": "Xandão",
          "slug": "xandao",
          "shortName": "Xandão",
          "position": "D",
          "jerseyNumber": "13",
          "userCount": 23,
          "id": 887270,
          "country": {
            "alpha2": "BR",
            "name": "Brazil"
          },
          "marketValueCurrency": "EUR",
          "dateOfBirthTimestamp": 642124800
        },
        "shirtNumber": 44,
        "jerseyNumber": "44",
        "position": "D",
        "substitute": true,
        "statistics": {}
      },
      {
        "player": {
          "name": "Ezequiel",
          "slug": "ezequiel",
          "shortName": "Ezequiel",
          "position": "D",
          "jerseyNumber": "16",
          "userCount": 33,
          "id": 311670,
          "country": {
            "alpha2": "BR",
            "name": "Brazil"
          },
          "marketValueCurrency": "EUR",
          "dateOfBirthTimestamp": 730339200
        },
        "shirtNumber": 22,
        "jerseyNumber": "22",
        "position": "D",
        "substitute": true,
        "statistics": {}
      },
      {
        "player": {
          "name": "Edson Fernando",
          "firstName": "",
          "lastName": "",
          "slug": "edson-fernando",
          "shortName": "Edson Fernando",
          "position": "M",
          "jerseyNumber": "35",
          "userCount": 40,
          "id": 988779,
          "country": {
            "alpha2": "BR",
            "name": "Brazil"
          },
          "marketValueCurrency": "EUR",
          "dateOfBirthTimestamp": 893376000,
          "fieldTranslations": {
            "nameTranslation": {
              "ar": "Edson"
            },
            "shortNameTranslation": {}
          }
        },
        "shirtNumber": 35,
        "jerseyNumber": "35",
        "position": "M",
        "substitute": true,
        "statistics": {}
      }
    ],
    "supportStaff": [],
    "formation": "4-3-3",
    "playerColor": {
      "primary": "0000ff",
      "number": "ffcc33",
      "outline": "0000ff",
      "fancyNumber": "ffffff"
    },
    "goalkeeperColor": {
      "primary": "ff0000",
      "number": "000000",
      "outline": "ff0000",
      "fancyNumber": "ffffff"
    }
  },
  "away": {
    "players": [
      {
        "player": {
          "name": "Weverton",
          "slug": "weverton",
          "shortName": "Weverton",
          "position": "G",
          "jerseyNumber": "21",
          "userCount": 2685,
          "id": 243529,
          "country": {
            "alpha2": "BR",
            "name": "Brazil"
          },
          "marketValueCurrency": "EUR",
          "dateOfBirthTimestamp": 566352000,
          "fieldTranslations": {
            "nameTranslation": {
              "ar": "ويفرتون"
            },
            "shortNameTranslation": {}
          }
        },
        "shirtNumber": 21,
        "jerseyNumber": "21",
        "position": "G",
        "substitute": false,
        "statistics": {
          "totalPass": 16,
          "accuratePass": 10,
          "totalLongBalls": 11,
          "accurateLongBalls": 5,
          "totalClearance": 3,
          "savedShotsFromInsideTheBox": 4,
          "saves": 4,
          "punches": 1,
          "minutesPlayed": 90,
          "touches": 29,
          "rating": 7.3,
          "possessionLostCtrl": 6
        }
      },
      {
        "player": {
          "name": "Marcos Rocha",
          "firstName": "",
          "lastName": "",
          "slug": "marcos-rocha",
          "shortName": "Marcos Rocha",
          "position": "D",
          "jerseyNumber": "2",
          "userCount": 976,
          "id": 82576,
          "country": {
            "alpha2": "BR",
            "name": "Brazil"
          },
          "marketValueCurrency": "EUR",
          "dateOfBirthTimestamp": 597801600
        },
        "shirtNumber": 2,
        "jerseyNumber": "2",
        "position": "D",
        "substitute": false,
        "statistics": {
          "totalPass": 62,
          "accuratePass": 50,
          "totalLongBalls": 10,
          "accurateLongBalls": 5,
          "totalCross": 5,
          "accurateCross": 2,
          "aerialLost": 1,
          "duelLost": 7,
          "duelWon": 6,
          "challengeLost": 3,
          "dispossessed": 1,
          "totalContest": 2,
          "wonContest": 1,
          "blockedScoringAttempt": 1,
          "totalClearance": 1,
          "interceptionWon": 2,
          "totalTackle": 4,
          "wasFouled": 1,
          "fouls": 1,
          "minutesPlayed": 90,
          "touches": 89,
          "rating": 7,
          "possessionLostCtrl": 18,
          "keyPass": 5
        }
      },
      {
        "player": {
          "name": "Luan",
          "firstName": "",
          "lastName": "",
          "slug": "luan",
          "shortName": "Luan",
          "position": "D",
          "jerseyNumber": "13",
          "userCount": 759,
          "id": 250351,
          "country": {
            "alpha2": "BR",
            "name": "Brazil"
          },
          "marketValueCurrency": "EUR",
          "dateOfBirthTimestamp": 736992000
        },
        "shirtNumber": 13,
        "jerseyNumber": "13",
        "position": "D",
        "substitute": false,
        "statistics": {
          "totalPass": 35,
          "accuratePass": 30,
          "totalLongBalls": 5,
          "accurateLongBalls": 2,
          "totalCross": 1,
          "aerialWon": 2,
          "duelLost": 2,
          "duelWon": 5,
          "totalContest": 1,
          "wonContest": 1,
          "totalClearance": 5,
          "outfielderBlock": 2,
          "totalTackle": 2,
          "fouls": 2,
          "minutesPlayed": 90,
          "touches": 49,
          "rating": 7.1,
          "possessionLostCtrl": 7
        }
      },
      {
        "player": {
          "name": "Vitor Hugo",
          "slug": "vitor-hugo",
          "shortName": "V. Hugo",
          "position": "D",
          "jerseyNumber": "31",
          "userCount": 340,
          "id": 794838,
          "country": {
            "alpha2": "BR",
            "name": "Brazil"
          },
          "marketValueCurrency": "EUR",
          "dateOfBirthTimestamp": 674697600,
          "fieldTranslations": {
            "nameTranslation": {
              "ar": "هوغو, فيتور"
            },
            "shortNameTranslation": {}
          }
        },
        "shirtNumber": 4,
        "jerseyNumber": "4",
        "position": "D",
        "substitute": false,
        "statistics": {
          "totalPass": 37,
          "accuratePass": 35,
          "totalLongBalls": 2,
          "accurateLongBalls": 2,
          "aerialLost": 3,
          "aerialWon": 3,
          "duelLost": 5,
          "duelWon": 3,
          "challengeLost": 2,
          "totalClearance": 5,
          "outfielderBlock": 1,
          "interceptionWon": 2,
          "minutesPlayed": 90,
          "touches": 47,
          "rating": 6.8,
          "possessionLostCtrl": 3
        }
      },
      {
        "player": {
          "name": "Diogo Barbosa",
          "slug": "diogo-barbosa",
          "shortName": "Diogo Barbosa",
          "position": "D",
          "jerseyNumber": "40",
          "userCount": 343,
          "id": 243107,
          "country": {
            "alpha2": "BR",
            "name": "Brazil"
          },
          "marketValueCurrency": "EUR",
          "dateOfBirthTimestamp": 714009600
        },
        "shirtNumber": 6,
        "jerseyNumber": "6",
        "position": "D",
        "substitute": false,
        "statistics": {
          "totalPass": 48,
          "accuratePass": 43,
          "totalLongBalls": 1,
          "accurateLongBalls": 1,
          "totalCross": 3,
          "duelLost": 6,
          "duelWon": 2,
          "challengeLost": 1,
          "dispossessed": 2,
          "totalContest": 1,
          "wonContest": 1,
          "totalClearance": 3,
          "interceptionWon": 1,
          "wasFouled": 1,
          "fouls": 3,
          "minutesPlayed": 90,
          "touches": 67,
          "rating": 6.5,
          "possessionLostCtrl": 11,
          "keyPass": 2
        }
      },
      {
        "player": {
          "name": "Bruno Henrique",
          "slug": "bruno-henrique",
          "shortName": "Bruno Henrique",
          "position": "M",
          "jerseyNumber": "8",
          "userCount": 389,
          "id": 345113,
          "country": {
            "alpha2": "BR",
            "name": "Brazil"
          },
          "marketValueCurrency": "EUR",
          "dateOfBirthTimestamp": 624931200,
          "fieldTranslations": {
            "nameTranslation": {
              "ar": "برونو هنريك"
            },
            "shortNameTranslation": {}
          }
        },
        "shirtNumber": 19,
        "jerseyNumber": "19",
        "position": "M",
        "substitute": false,
        "captain": true,
        "statistics": {
          "totalPass": 62,
          "accuratePass": 56,
          "totalLongBalls": 4,
          "accurateLongBalls": 3,
          "aerialLost": 3,
          "duelLost": 3,
          "bigChanceMissed": 1,
          "shotOffTarget": 3,
          "onTargetScoringAttempt": 1,
          "blockedScoringAttempt": 1,
          "totalClearance": 1,
          "minutesPlayed": 90,
          "touches": 73,
          "rating": 6.6,
          "possessionLostCtrl": 9
        }
      },
      {
        "player": {
          "name": "Thiago Santos",
          "firstName": "",
          "lastName": "",
          "slug": "thiago-santos",
          "shortName": "Thiago Santos",
          "position": "M",
          "jerseyNumber": "29",
          "userCount": 279,
          "id": 378590,
          "country": {
            "alpha2": "BR",
            "name": "Brazil"
          },
          "marketValueCurrency": "EUR",
          "dateOfBirthTimestamp": 620956800
        },
        "shirtNumber": 5,
        "jerseyNumber": "5",
        "position": "M",
        "substitute": false,
        "statistics": {
          "totalPass": 49,
          "accuratePass": 45,
          "totalLongBalls": 3,
          "accurateLongBalls": 2,
          "aerialLost": 3,
          "duelLost": 8,
          "duelWon": 7,
          "challengeLost": 1,
          "dispossessed": 1,
          "totalContest": 1,
          "wonContest": 1,
          "interceptionWon": 3,
          "totalTackle": 3,
          "wasFouled": 3,
          "fouls": 4,
          "minutesPlayed": 90,
          "touches": 61,
          "rating": 7.1,
          "possessionLostCtrl": 5,
          "keyPass": 2
        }
      },
      {
        "player": {
          "name": "Gustavo Scarpa",
          "firstName": "",
          "lastName": "",
          "slug": "gustavo-scarpa",
          "shortName": "Gustavo Scarpa",
          "position": "M",
          "jerseyNumber": "31",
          "userCount": 6377,
          "id": 559036,
          "country": {
            "alpha2": "BR",
            "name": "Brazil"
          },
          "marketValueCurrency": "EUR",
          "dateOfBirthTimestamp": 757728000,
          "fieldTranslations": {
            "nameTranslation": {
              "ar": "سكاربا, غوستافو"
            },
            "shortNameTranslation": {}
          }
        },
        "shirtNumber": 14,
        "jerseyNumber": "14",
        "position": "M",
        "substitute": false,
        "statistics": {
          "totalPass": 22,
          "accuratePass": 17,
          "totalLongBalls": 2,
          "accurateLongBalls": 1,
          "totalCross": 1,
          "aerialWon": 1,
          "duelLost": 2,
          "duelWon": 4,
          "dispossessed": 1,
          "totalContest": 2,
          "wonContest": 1,
          "shotOffTarget": 1,
          "outfielderBlock": 1,
          "interceptionWon": 1,
          "wasFouled": 2,
          "fouls": 1,
          "minutesPlayed": 45,
          "touches": 33,
          "rating": 6.8,
          "possessionLostCtrl": 9
        }
      },
      {
        "player": {
          "name": "Dudu",
          "firstName": "",
          "lastName": "",
          "slug": "dudu",
          "shortName": "Dudu",
          "position": "M",
          "jerseyNumber": "7",
          "userCount": 4183,
          "id": 147464,
          "country": {
            "alpha2": "BR",
            "name": "Brazil"
          },
          "marketValueCurrency": "EUR",
          "dateOfBirthTimestamp": 694742400,
          "fieldTranslations": {
            "nameTranslation": {
              "ar": "دودو"
            },
            "shortNameTranslation": {}
          }
        },
        "shirtNumber": 7,
        "jerseyNumber": "7",
        "position": "M",
        "substitute": false,
        "statistics": {
          "totalPass": 44,
          "accuratePass": 38,
          "totalLongBalls": 5,
          "accurateLongBalls": 5,
          "totalCross": 7,
          "accurateCross": 1,
          "aerialLost": 2,
          "duelLost": 4,
          "duelWon": 3,
          "challengeLost": 1,
          "dispossessed": 1,
          "totalContest": 1,
          "wonContest": 1,
          "bigChanceCreated": 1,
          "shotOffTarget": 1,
          "onTargetScoringAttempt": 2,
          "totalTackle": 1,
          "wasFouled": 1,
          "minutesPlayed": 90,
          "touches": 64,
          "rating": 7.9,
          "possessionLostCtrl": 16,
          "keyPass": 3
        }
      },
      {
        "player": {
          "name": "Zé Rafael",
          "slug": "ze-rafael",
          "shortName": "Z. Rafael",
          "position": "M",
          "jerseyNumber": "8",
          "userCount": 1391,
          "id": 329069,
          "country": {
            "alpha2": "BR",
            "name": "Brazil"
          },
          "marketValueCurrency": "EUR",
          "dateOfBirthTimestamp": 740188800
        },
        "shirtNumber": 8,
        "jerseyNumber": "8",
        "position": "M",
        "substitute": false,
        "statistics": {
          "totalPass": 32,
          "accuratePass": 29,
          "goalAssist": 1,
          "totalCross": 1,
          "aerialLost": 1,
          "aerialWon": 2,
          "duelLost": 4,
          "duelWon": 9,
          "challengeLost": 1,
          "dispossessed": 1,
          "totalContest": 1,
          "wonContest": 1,
          "shotOffTarget": 2,
          "totalTackle": 1,
          "wasFouled": 5,
          "fouls": 1,
          "minutesPlayed": 72,
          "touches": 46,
          "rating": 7.4,
          "possessionLostCtrl": 7,
          "keyPass": 1
        }
      },
      {
        "player": {
          "name": "Deyverson",
          "firstName": "",
          "lastName": "",
          "slug": "deyverson",
          "shortName": "Deyverson",
          "position": "F",
          "jerseyNumber": "16",
          "userCount": 1846,
          "id": 270287,
          "country": {
            "alpha2": "BR",
            "name": "Brazil"
          },
          "marketValueCurrency": "EUR",
          "dateOfBirthTimestamp": 673660800,
          "fieldTranslations": {
            "nameTranslation": {
              "ar": "ديفيرسون"
            },
            "shortNameTranslation": {}
          }
        },
        "shirtNumber": 16,
        "jerseyNumber": "16",
        "position": "F",
        "substitute": false,
        "statistics": {
          "totalPass": 8,
          "accuratePass": 6,
          "totalLongBalls": 1,
          "totalCross": 1,
          "aerialLost": 1,
          "duelLost": 5,
          "duelWon": 2,
          "dispossessed": 2,
          "totalContest": 1,
          "blockedScoringAttempt": 2,
          "totalTackle": 1,
          "wasFouled": 1,
          "fouls": 1,
          "minutesPlayed": 45,
          "touches": 18,
          "rating": 6.3,
          "possessionLostCtrl": 6
        }
      },
      {
        "player": {
          "name": "Lucas Lima",
          "slug": "lucas-lima",
          "shortName": "L. Lima",
          "position": "M",
          "jerseyNumber": "23",
          "userCount": 988,
          "id": 244589,
          "country": {
            "alpha2": "BR",
            "name": "Brazil"
          },
          "marketValueCurrency": "EUR",
          "dateOfBirthTimestamp": 647481600
        },
        "shirtNumber": 20,
        "jerseyNumber": "20",
        "position": "M",
        "substitute": true,
        "statistics": {
          "totalPass": 50,
          "accuratePass": 44,
          "totalLongBalls": 4,
          "accurateLongBalls": 2,
          "totalCross": 1,
          "duelLost": 2,
          "duelWon": 2,
          "challengeLost": 1,
          "totalContest": 1,
          "wonContest": 1,
          "shotOffTarget": 1,
          "onTargetScoringAttempt": 1,
          "wasFouled": 1,
          "fouls": 1,
          "minutesPlayed": 45,
          "touches": 55,
          "rating": 7.2,
          "possessionLostCtrl": 7,
          "keyPass": 3
        }
      },
      {
        "player": {
          "name": "Miguel Borja",
          "firstName": "",
          "lastName": "",
          "slug": "miguel-borja",
          "shortName": "Miguel Borja",
          "position": "F",
          "jerseyNumber": "9",
          "userCount": 2347,
          "id": 329601,
          "country": {
            "alpha2": "CO",
            "name": "Colombia"
          },
          "marketValueCurrency": "EUR",
          "dateOfBirthTimestamp": 728006400
        },
        "shirtNumber": 9,
        "jerseyNumber": "9",
        "position": "F",
        "substitute": true,
        "statistics": {
          "totalPass": 8,
          "accuratePass": 8,
          "aerialLost": 2,
          "aerialWon": 2,
          "duelLost": 3,
          "duelWon": 3,
          "totalContest": 1,
          "shotOffTarget": 4,
          "onTargetScoringAttempt": 1,
          "goals": 1,
          "totalClearance": 1,
          "outfielderBlock": 1,
          "totalTackle": 1,
          "wasFouled": 1,
          "fouls": 1,
          "minutesPlayed": 45,
          "touches": 22,
          "rating": 7.8,
          "possessionLostCtrl": 1,
          "keyPass": 1
        }
      },
      {
        "player": {
          "name": "Willian",
          "firstName": "",
          "lastName": "",
          "slug": "willian",
          "shortName": "Willian",
          "position": "F",
          "jerseyNumber": "11",
          "userCount": 606,
          "id": 146308,
          "country": {
            "alpha2": "BR",
            "name": "Brazil"
          },
          "marketValueCurrency": "EUR",
          "dateOfBirthTimestamp": 532742400,
          "fieldTranslations": {
            "nameTranslation": {
              "ar": "ويليان"
            },
            "shortNameTranslation": {}
          }
        },
        "shirtNumber": 29,
        "jerseyNumber": "29",
        "position": "F",
        "substitute": true,
        "statistics": {
          "totalPass": 8,
          "accuratePass": 8,
          "totalLongBalls": 1,
          "accurateLongBalls": 1,
          "duelLost": 3,
          "duelWon": 1,
          "totalContest": 2,
          "shotOffTarget": 1,
          "interceptionWon": 1,
          "wasFouled": 1,
          "fouls": 1,
          "minutesPlayed": 18,
          "touches": 15,
          "rating": 6.2,
          "possessionLostCtrl": 4,
          "keyPass": 2
        }
      },
      {
        "player": {
          "name": "Fernando Prass",
          "slug": "fernando-prass",
          "shortName": "F. Prass",
          "position": "G",
          "jerseyNumber": "1",
          "userCount": 187,
          "id": 14270,
          "country": {
            "alpha2": "BR",
            "name": "Brazil"
          },
          "marketValueCurrency": "EUR",
          "dateOfBirthTimestamp": 268790400
        },
        "shirtNumber": 1,
        "jerseyNumber": "1",
        "position": "G",
        "substitute": true,
        "statistics": {}
      },
      {
        "player": {
          "name": "Antônio Carlos",
          "slug": "antonio-carlos",
          "shortName": "A. Carlos",
          "position": "D",
          "jerseyNumber": "25",
          "userCount": 161,
          "id": 242209,
          "country": {
            "alpha2": "BR",
            "name": "Brazil"
          },
          "marketValueCurrency": "EUR",
          "dateOfBirthTimestamp": 731462400
        },
        "shirtNumber": 25,
        "jerseyNumber": "25",
        "position": "D",
        "substitute": true,
        "statistics": {}
      },
      {
        "player": {
          "name": "Edu Dracena",
          "slug": "edu-dracena",
          "shortName": "E. Dracena",
          "position": "D",
          "jerseyNumber": "3",
          "userCount": 59,
          "id": 18763,
          "country": {
            "alpha2": "BR",
            "name": "Brazil"
          },
          "marketValueCurrency": "EUR",
          "dateOfBirthTimestamp": 358992000
        },
        "shirtNumber": 3,
        "jerseyNumber": "3",
        "position": "D",
        "substitute": true,
        "statistics": {}
      },
      {
        "player": {
          "name": "Victor Luis",
          "firstName": "",
          "lastName": "",
          "slug": "victor-luis",
          "shortName": "Victor Luis",
          "position": "D",
          "jerseyNumber": "26",
          "userCount": 257,
          "id": 252781,
          "country": {
            "alpha2": "BR",
            "name": "Brazil"
          },
          "marketValueCurrency": "EUR",
          "dateOfBirthTimestamp": 740793600
        },
        "shirtNumber": 26,
        "jerseyNumber": "26",
        "position": "D",
        "substitute": true,
        "statistics": {}
      },
      {
        "player": {
          "name": "Mayke",
          "slug": "mayke",
          "shortName": "Mayke",
          "position": "D",
          "jerseyNumber": "12",
          "userCount": 937,
          "id": 273329,
          "country": {
            "alpha2": "BR",
            "name": "Brazil"
          },
          "marketValueCurrency": "EUR",
          "dateOfBirthTimestamp": 721353600,
          "fieldTranslations": {
            "nameTranslation": {
              "ar": "مايكي"
            },
            "shortNameTranslation": {}
          }
        },
        "shirtNumber": 12,
        "jerseyNumber": "12",
        "position": "D",
        "substitute": true,
        "statistics": {}
      },
      {
        "player": {
          "name": "Hyoran",
          "firstName": "",
          "lastName": "",
          "slug": "hyoran",
          "shortName": "Hyoran",
          "position": "M",
          "userCount": 468,
          "id": 551348,
          "country": {
            "alpha2": "BR",
            "name": "Brazil"
          },
          "marketValueCurrency": "EUR",
          "dateOfBirthTimestamp": 738288000,
          "fieldTranslations": {
            "nameTranslation": {
              "ar": "هيوران"
            },
            "shortNameTranslation": {}
          }
        },
        "shirtNumber": 28,
        "jerseyNumber": "28",
        "position": "M",
        "substitute": true,
        "statistics": {}
      },
      {
        "player": {
          "name": "Ramires",
          "slug": "ramires",
          "shortName": "Ramires",
          "position": "M",
          "jerseyNumber": "7",
          "userCount": 309,
          "id": 33110,
          "country": {
            "alpha2": "BR",
            "name": "Brazil"
          },
          "marketValueCurrency": "EUR",
          "dateOfBirthTimestamp": 543542400
        },
        "shirtNumber": 18,
        "jerseyNumber": "18",
        "position": "M",
        "substitute": true,
        "statistics": {}
      },
      {
        "player": {
          "name": "Matheus Fernandes",
          "firstName": "",
          "lastName": "",
          "slug": "matheus-fernandes",
          "shortName": "Matheus Fernandes",
          "position": "M",
          "jerseyNumber": "35",
          "userCount": 1014,
          "id": 840150,
          "country": {
            "alpha2": "BR",
            "name": "Brazil"
          },
          "marketValueCurrency": "EUR",
          "dateOfBirthTimestamp": 899164800
        },
        "shirtNumber": 35,
        "jerseyNumber": "35",
        "position": "M",
        "substitute": true,
        "statistics": {}
      },
      {
        "player": {
          "name": "Raphael Veiga",
          "firstName": "",
          "lastName": "",
          "slug": "raphael-veiga",
          "shortName": "Raphael Veiga",
          "position": "M",
          "jerseyNumber": "23",
          "userCount": 8015,
          "id": 840020,
          "country": {
            "alpha2": "BR",
            "name": "Brazil"
          },
          "marketValueCurrency": "EUR",
          "dateOfBirthTimestamp": 803520000,
          "fieldTranslations": {
            "nameTranslation": {
              "ar": "رافائيل فييغا"
            },
            "shortNameTranslation": {}
          }
        },
        "shirtNumber": 23,
        "jerseyNumber": "23",
        "position": "M",
        "substitute": true,
        "statistics": {}
      }
    ],
    "supportStaff": [],
    "formation": "4-2-3-1",
    "playerColor": {
      "primary": "ffffff",
      "number": "000000",
      "outline": "ffffff",
      "fancyNumber": "222226"
    },
    "goalkeeperColor": {
      "primary": "ffffff",
      "number": "339900",
      "outline": "ffffff",
      "fancyNumber": "222226"
    }
  }
}