{
  "shotmap": [
    {
      "player": {
        "name": "Richard Ríos",
        "slug": "richard-rios",
        "shortName": "R. Ríos",
        "position": "M",
        "userCount": 2199,
        "id": 1015292
      },
      "isHome": false,
      "shotType": "miss",
      "situation": "assisted",
      "playerCoordinates": {
        "x": 31.4,
        "y": 55.1,
        "z": 0
      },
      "bodyPart": "right-foot",
      "goalMouthLocation": "high",
      "goalMouthCoordinates": {
        "x": 0,
        "y": 44.4,
        "z": 93.1
      },
      "xg": 0.012135903351009,
      "id": 2083984,
      "time": 90,
      "addedTime": 4,
      "timeSeconds": 5637,
      "draw": {
        "start": {
          "x": 55.1,
          "y": 31.4
        },
        "end": {
          "x": 55.6,
          "y": 0
        },
        "goal": {
          "x": 55.6,
          "y": 6.9
        }
      },
      "reversedPeriodTime": 1,
      "reversedPeriodTimeSeconds": 663,
      "incidentType": "shot"
    },
    {
      "player": {
        "name": "Thaciano",
        "slug": "thaciano",
        "shortName": "Thaciano",
        "position": "M",
        "userCount": 438,
        "id": 872039,
        "fieldTranslations": {
          "nameTranslation": {
            "ar": "ثاسيانو"
          },
          "shortNameTranslation": {}
        }
      },
      "isHome": true,
      "shotType": "goal",
      "goalType": "regular",
      "situation": "regular",
      "playerCoordinates": {
        "x": 5.3,
        "y": 46.1,
        "z": 0
      },
      "bodyPart": "left-foot",
      "goalMouthLocation": "low-centre",
      "goalMouthCoordinates": {
        "x": 0,
        "y": 51.4,
        "z": 7.6
      },
      "xg": 0.69088315963745,
      "xgot": 0.7477,
      "id": 2083983,
      "time": 90,
      "addedTime": 3,
      "timeSeconds": 5555,
      "draw": {
        "start": {
          "x": 46.1,
          "y": 5.3
        },
        "end": {
          "x": 48.6,
          "y": 0
        },
        "goal": {
          "x": 48.6,
          "y": 92.4
        }
      },
      "reversedPeriodTime": 1,
      "reversedPeriodTimeSeconds": 745,
      "incidentType": "shot"
    },
    {
      "player": {
        "name": "Danielzinho",
        "slug": "danielzinho",
        "shortName": "Danielzinho",
        "position": "M",
        "userCount": 293,
        "id": 840218
      },
      "isHome": true,
      "shotType": "save",
      "situation": "regular",
      "playerCoordinates": {
        "x": 15.7,
        "y": 66.7,
        "z": 0
      },
      "bodyPart": "right-foot",
      "goalMouthLocation": "low-left",
      "goalMouthCoordinates": {
        "x": 0,
        "y": 52.9,
        "z": 5.7
      },
      "blockCoordinates": {
        "x": 1.9,
        "y": 51.3,
        "z": 0
      },
      "xg": 0.043027374893427,
      "xgot": 0.2234,
      "id": 2083981,
      "time": 90,
      "addedTime": 3,
      "timeSeconds": 5552,
      "draw": {
        "start": {
          "x": 66.7,
          "y": 15.7
        },
        "block": {
          "x": 51.3,
          "y": 1.9
        },
        "end": {
          "x": 47.1,
          "y": 0
        },
        "goal": {
          "x": 47.1,
          "y": 94.3
        }
      },
      "reversedPeriodTime": 1,
      "reversedPeriodTimeSeconds": 748,
      "incidentType": "shot"
    },
    {
      "player": {
        "name": "Breno Lopes",
        "firstName": "",
        "lastName": "",
        "slug": "breno-lopes",
        "shortName": "Breno Lopes",
        "position": "F",
        "userCount": 782,
        "id": 937552
      },
      "isHome": false,
      "shotType": "block",
      "situation": "regular",
      "playerCoordinates": {
        "x": 5.7,
        "y": 33.2,
        "z": 0
      },
      "bodyPart": "left-foot",
      "goalMouthLocation": "low-centre",
      "goalMouthCoordinates": {
        "x": 0,
        "y": 50.9,
        "z": 19
      },
      "blockCoordinates": {
        "x": 5.1,
        "y": 35,
        "z": 0
      },
      "xg": 0.058350585401058,
      "id": 2083980,
      "time": 90,
      "timeSeconds": 5391,
      "draw": {
        "start": {
          "x": 33.2,
          "y": 5.7
        },
        "block": {
          "x": 35,
          "y": 5.1
        },
        "end": {
          "x": 49.1,
          "y": 0
        },
        "goal": {
          "x": 49.1,
          "y": 81
        }
      },
      "reversedPeriodTime": 1,
      "reversedPeriodTimeSeconds": 9,
      "incidentType": "shot"
    },
    {
      "player": {
        "name": "Kayky",
        "firstName": "Kayky",
        "slug": "kayky",
        "shortName": "Kayky",
        "position": "M",
        "userCount": 2124,
        "id": 1106151
      },
      "isHome": true,
      "shotType": "block",
      "situation": "fast-break",
      "playerCoordinates": {
        "x": 17.1,
        "y": 54.8,
        "z": 0
      },
      "bodyPart": "left-foot",
      "goalMouthLocation": "low-left",
      "goalMouthCoordinates": {
        "x": 0,
        "y": 53.6,
        "z": 19
      },
      "blockCoordinates": {
        "x": 15.8,
        "y": 54.2,
        "z": 0
      },
      "xg": 0.095087520778179,
      "id": 2083944,
      "time": 70,
      "timeSeconds": 4177,
      "draw": {
        "start": {
          "x": 54.8,
          "y": 17.1
        },
        "block": {
          "x": 54.2,
          "y": 15.8
        },
        "end": {
          "x": 46.4,
          "y": 0
        },
        "goal": {
          "x": 46.4,
          "y": 81
        }
      },
      "reversedPeriodTime": 21,
      "reversedPeriodTimeSeconds": 1223,
      "incidentType": "shot"
    },
    {
      "player": {
        "name": "Jhoanner Chávez",
        "firstName": "",
        "lastName": "",
        "slug": "jhoanner-chavez",
        "shortName": "Jhoanner Chávez",
        "position": "D",
        "userCount": 375,
        "id": 1002458
      },
      "isHome": true,
      "shotType": "miss",
      "situation": "assisted",
      "playerCoordinates": {
        "x": 15.8,
        "y": 32.1,
        "z": 0
      },
      "bodyPart": "left-foot",
      "goalMouthLocation": "high",
      "goalMouthCoordinates": {
        "x": 0,
        "y": 55.8,
        "z": 80.6
      },
      "xg": 0.04801744222641,
      "id": 2083937,
      "time": 68,
      "timeSeconds": 4074,
      "draw": {
        "start": {
          "x": 32.1,
          "y": 15.8
        },
        "end": {
          "x": 44.2,
          "y": 0
        },
        "goal": {
          "x": 44.2,
          "y": 19.4
        }
      },
      "reversedPeriodTime": 23,
      "reversedPeriodTimeSeconds": 1326,
      "incidentType": "shot"
    },
    {
      "player": {
        "name": "Vitor Hugo",
        "slug": "vitor-hugo",
        "shortName": "V. Hugo",
        "position": "D",
        "userCount": 330,
        "id": 794838,
        "fieldTranslations": {
          "nameTranslation": {
            "ar": "هوغو, فيتور"
          },
          "shortNameTranslation": {}
        }
      },
      "isHome": true,
      "shotType": "miss",
      "situation": "corner",
      "playerCoordinates": {
        "x": 9.2,
        "y": 48.5,
        "z": 0
      },
      "bodyPart": "right-foot",
      "goalMouthLocation": "right",
      "goalMouthCoordinates": {
        "x": 0,
        "y": 33.1,
        "z": 11.1
      },
      "blockCoordinates": {
        "x": 2.4,
        "y": 66.8,
        "z": 0
      },
      "xg": 0.077849842607975,
      "id": 2083938,
      "time": 68,
      "timeSeconds": 4031,
      "draw": {
        "start": {
          "x": 48.5,
          "y": 9.2
        },
        "block": {
          "x": 66.8,
          "y": 2.4
        },
        "end": {
          "x": 66.9,
          "y": 0
        },
        "goal": {
          "x": 66.9,
          "y": 88.9
        }
      },
      "reversedPeriodTime": 23,
      "reversedPeriodTimeSeconds": 1369,
      "incidentType": "shot"
    },
    {
      "player": {
        "name": "Dudu",
        "firstName": "",
        "lastName": "",
        "slug": "dudu",
        "shortName": "Dudu",
        "position": "M",
        "userCount": 4177,
        "id": 147464,
        "fieldTranslations": {
          "nameTranslation": {
            "ar": "دودو"
          },
          "shortNameTranslation": {}
        }
      },
      "isHome": false,
      "shotType": "save",
      "situation": "assisted",
      "playerCoordinates": {
        "x": 8.8,
        "y": 37.8,
        "z": 0
      },
      "bodyPart": "right-foot",
      "goalMouthLocation": "low-centre",
      "goalMouthCoordinates": {
        "x": 0,
        "y": 49.2,
        "z": 12.7
      },
      "blockCoordinates": {
        "x": 7.1,
        "y": 40.1,
        "z": 0
      },
      "xg": 0.080922812223434,
      "xgot": 0.0331,
      "id": 2083915,
      "time": 56,
      "timeSeconds": 3358,
      "draw": {
        "start": {
          "x": 37.8,
          "y": 8.8
        },
        "block": {
          "x": 40.1,
          "y": 7.1
        },
        "end": {
          "x": 50.8,
          "y": 0
        },
        "goal": {
          "x": 50.8,
          "y": 87.3
        }
      },
      "reversedPeriodTime": 35,
      "reversedPeriodTimeSeconds": 2042,
      "incidentType": "shot"
    },
    {
      "player": {
        "name": "Kanu",
        "firstName": "",
        "lastName": "",
        "slug": "kanu",
        "shortName": "Kanu",
        "position": "D",
        "userCount": 274,
        "id": 871705,
        "fieldTranslations": {
          "nameTranslation": {
            "ar": "كانو"
          },
          "shortNameTranslation": {}
        }
      },
      "isHome": true,
      "shotType": "miss",
      "situation": "corner",
      "playerCoordinates": {
        "x": 12.6,
        "y": 51.2,
        "z": 0
      },
      "bodyPart": "head",
      "goalMouthLocation": "left",
      "goalMouthCoordinates": {
        "x": 0,
        "y": 71.3,
        "z": 6.9
      },
      "blockCoordinates": {
        "x": 1.1,
        "y": 30.5,
        "z": 0
      },
      "xg": 0.03175064176321,
      "id": 2083910,
      "time": 55,
      "timeSeconds": 3277,
      "draw": {
        "start": {
          "x": 51.2,
          "y": 12.6
        },
        "block": {
          "x": 30.5,
          "y": 1.1
        },
        "end": {
          "x": 28.7,
          "y": 0
        },
        "goal": {
          "x": 28.7,
          "y": 93.1
        }
      },
      "reversedPeriodTime": 36,
      "reversedPeriodTimeSeconds": 2123,
      "incidentType": "shot"
    },
    {
      "player": {
        "name": "Artur",
        "firstName": "",
        "lastName": "",
        "slug": "artur",
        "shortName": "Artur",
        "position": "M",
        "userCount": 2285,
        "id": 841128,
        "fieldTranslations": {
          "nameTranslation": {
            "ar": "أرثور"
          },
          "shortNameTranslation": {}
        }
      },
      "isHome": false,
      "shotType": "save",
      "situation": "assisted",
      "playerCoordinates": {
        "x": 11.5,
        "y": 68.2,
        "z": 0
      },
      "bodyPart": "right-foot",
      "goalMouthLocation": "low-right",
      "goalMouthCoordinates": {
        "x": 0,
        "y": 46.2,
        "z": 3.2
      },
      "blockCoordinates": {
        "x": 1.4,
        "y": 52.9,
        "z": 0
      },
      "xg": 0.070319153368473,
      "xgot": 0.2047,
      "id": 2083828,
      "time": 45,
      "addedTime": 1,
      "timeSeconds": 2748,
      "draw": {
        "start": {
          "x": 68.2,
          "y": 11.5
        },
        "block": {
          "x": 52.9,
          "y": 1.4
        },
        "end": {
          "x": 53.8,
          "y": 0
        },
        "goal": {
          "x": 53.8,
          "y": 96.8
        }
      },
      "reversedPeriodTime": 1,
      "reversedPeriodTimeSeconds": 2652,
      "incidentType": "shot"
    },
    {
      "player": {
        "name": "Dudu",
        "firstName": "",
        "lastName": "",
        "slug": "dudu",
        "shortName": "Dudu",
        "position": "M",
        "userCount": 4177,
        "id": 147464,
        "fieldTranslations": {
          "nameTranslation": {
            "ar": "دودو"
          },
          "shortNameTranslation": {}
        }
      },
      "isHome": false,
      "shotType": "miss",
      "situation": "assisted",
      "playerCoordinates": {
        "x": 13.4,
        "y": 36.3,
        "z": 0
      },
      "bodyPart": "head",
      "goalMouthLocation": "close-left",
      "goalMouthCoordinates": {
        "x": 0,
        "y": 58.5,
        "z": 9.7
      },
      "xg": 0.01503196451813,
      "id": 2083821,
      "time": 45,
      "timeSeconds": 2676,
      "draw": {
        "start": {
          "x": 36.3,
          "y": 13.4
        },
        "end": {
          "x": 41.5,
          "y": 0
        },
        "goal": {
          "x": 41.5,
          "y": 90.3
        }
      },
      "reversedPeriodTime": 1,
      "reversedPeriodTimeSeconds": 24,
      "incidentType": "shot"
    },
    {
      "player": {
        "name": "Artur",
        "firstName": "",
        "lastName": "",
        "slug": "artur",
        "shortName": "Artur",
        "position": "M",
        "userCount": 2285,
        "id": 841128,
        "fieldTranslations": {
          "nameTranslation": {
            "ar": "أرثور"
          },
          "shortNameTranslation": {}
        }
      },
      "isHome": false,
      "shotType": "miss",
      "situation": "fast-break",
      "playerCoordinates": {
        "x": 14,
        "y": 60.6,
        "z": 0
      },
      "bodyPart": "left-foot",
      "goalMouthLocation": "left",
      "goalMouthCoordinates": {
        "x": 0,
        "y": 62,
        "z": 2.8
      },
      "xg": 0.1320561170578,
      "id": 2083791,
      "time": 39,
      "timeSeconds": 2304,
      "draw": {
        "start": {
          "x": 60.6,
          "y": 14
        },
        "end": {
          "x": 38,
          "y": 0
        },
        "goal": {
          "x": 38,
          "y": 97.2
        }
      },
      "reversedPeriodTime": 7,
      "reversedPeriodTimeSeconds": 396,
      "incidentType": "shot"
    },
    {
      "player": {
        "name": "Endrick",
        "firstName": "",
        "lastName": "",
        "slug": "endrick",
        "shortName": "Endrick",
        "position": "F",
        "userCount": 36973,
        "id": 1174937,
        "fieldTranslations": {
          "nameTranslation": {
            "ar": "إندريك"
          },
          "shortNameTranslation": {}
        }
      },
      "isHome": false,
      "shotType": "miss",
      "situation": "corner",
      "playerCoordinates": {
        "x": 8.3,
        "y": 57.2,
        "z": 0
      },
      "bodyPart": "left-foot",
      "goalMouthLocation": "left",
      "goalMouthCoordinates": {
        "x": 0,
        "y": 94.3,
        "z": 11.1
      },
      "blockCoordinates": {
        "x": 3.2,
        "y": 2.9,
        "z": 0
      },
      "xg": 0.13481555879116,
      "id": 2083800,
      "time": 34,
      "timeSeconds": 2003,
      "draw": {
        "start": {
          "x": 57.2,
          "y": 8.3
        },
        "block": {
          "x": 2.9,
          "y": 3.2
        },
        "end": {
          "x": 5.7,
          "y": 0
        },
        "goal": {
          "x": 5.7,
          "y": 88.9
        }
      },
      "reversedPeriodTime": 12,
      "reversedPeriodTimeSeconds": 697,
      "incidentType": "shot"
    },
    {
      "player": {
        "name": "Endrick",
        "firstName": "",
        "lastName": "",
        "slug": "endrick",
        "shortName": "Endrick",
        "position": "F",
        "userCount": 36973,
        "id": 1174937,
        "fieldTranslations": {
          "nameTranslation": {
            "ar": "إندريك"
          },
          "shortNameTranslation": {}
        }
      },
      "isHome": false,
      "shotType": "block",
      "situation": "assisted",
      "playerCoordinates": {
        "x": 5.1,
        "y": 45.8,
        "z": 0
      },
      "bodyPart": "left-foot",
      "goalMouthLocation": "low-centre",
      "goalMouthCoordinates": {
        "x": 0,
        "y": 51.3,
        "z": 19
      },
      "blockCoordinates": {
        "x": 3.5,
        "y": 46.7,
        "z": 0
      },
      "xg": 0.23911544680595,
      "id": 2083808,
      "time": 33,
      "timeSeconds": 1968,
      "draw": {
        "start": {
          "x": 45.8,
          "y": 5.1
        },
        "block": {
          "x": 46.7,
          "y": 3.5
        },
        "end": {
          "x": 48.7,
          "y": 0
        },
        "goal": {
          "x": 48.7,
          "y": 81
        }
      },
      "reversedPeriodTime": 13,
      "reversedPeriodTimeSeconds": 732,
      "incidentType": "shot"
    },
    {
      "player": {
        "name": "Artur",
        "firstName": "",
        "lastName": "",
        "slug": "artur",
        "shortName": "Artur",
        "position": "M",
        "userCount": 2285,
        "id": 841128,
        "fieldTranslations": {
          "nameTranslation": {
            "ar": "أرثور"
          },
          "shortNameTranslation": {}
        }
      },
      "isHome": false,
      "shotType": "miss",
      "situation": "assisted",
      "playerCoordinates": {
        "x": 32.9,
        "y": 72,
        "z": 0
      },
      "bodyPart": "left-foot",
      "goalMouthLocation": "high",
      "goalMouthCoordinates": {
        "x": 0,
        "y": 45,
        "z": 72.2
      },
      "xg": 0.020192550495267,
      "id": 2083763,
      "time": 31,
      "timeSeconds": 1819,
      "draw": {
        "start": {
          "x": 72,
          "y": 32.9
        },
        "end": {
          "x": 55,
          "y": 0
        },
        "goal": {
          "x": 55,
          "y": 27.8
        }
      },
      "reversedPeriodTime": 15,
      "reversedPeriodTimeSeconds": 881,
      "incidentType": "shot"
    },
    {
      "player": {
        "name": "Zé Rafael",
        "slug": "ze-rafael",
        "shortName": "Z. Rafael",
        "position": "M",
        "userCount": 1385,
        "id": 329069
      },
      "isHome": false,
      "shotType": "miss",
      "situation": "regular",
      "playerCoordinates": {
        "x": 22.9,
        "y": 43.3,
        "z": 0
      },
      "bodyPart": "right-foot",
      "goalMouthLocation": "close-right",
      "goalMouthCoordinates": {
        "x": 0,
        "y": 41.5,
        "z": 31.9
      },
      "xg": 0.025501294061542,
      "id": 2083747,
      "time": 25,
      "timeSeconds": 1467,
      "draw": {
        "start": {
          "x": 43.3,
          "y": 22.9
        },
        "end": {
          "x": 58.5,
          "y": 0
        },
        "goal": {
          "x": 58.5,
          "y": 68.1
        }
      },
      "reversedPeriodTime": 21,
      "reversedPeriodTimeSeconds": 1233,
      "incidentType": "shot"
    },
    {
      "player": {
        "name": "Nicolás Acevedo",
        "firstName": "",
        "lastName": "",
        "slug": "nicolas-acevedo",
        "shortName": "Nicolás Acevedo",
        "position": "M",
        "userCount": 318,
        "id": 959620
      },
      "isHome": true,
      "shotType": "save",
      "situation": "assisted",
      "playerCoordinates": {
        "x": 30.8,
        "y": 40.6,
        "z": 0
      },
      "bodyPart": "right-foot",
      "goalMouthLocation": "low-left",
      "goalMouthCoordinates": {
        "x": 0,
        "y": 54.3,
        "z": 2.5
      },
      "blockCoordinates": {
        "x": 0.7,
        "y": 50.4,
        "z": 0
      },
      "xg": 0.020439563319087,
      "xgot": 0.3659,
      "id": 2083716,
      "time": 19,
      "timeSeconds": 1112,
      "draw": {
        "start": {
          "x": 40.6,
          "y": 30.8
        },
        "block": {
          "x": 50.4,
          "y": 0.7
        },
        "end": {
          "x": 45.7,
          "y": 0
        },
        "goal": {
          "x": 45.7,
          "y": 97.5
        }
      },
      "reversedPeriodTime": 27,
      "reversedPeriodTimeSeconds": 1588,
      "incidentType": "shot"
    },
    {
      "player": {
        "name": "Cauly",
        "firstName": "",
        "lastName": "",
        "slug": "cauly",
        "shortName": "Cauly",
        "position": "M",
        "userCount": 981,
        "id": 255873,
        "fieldTranslations": {
          "nameTranslation": {
            "ar": "كولي اوليفيرا سوزا"
          },
          "shortNameTranslation": {}
        }
      },
      "isHome": true,
      "shotType": "miss",
      "situation": "regular",
      "playerCoordinates": {
        "x": 15.2,
        "y": 45.8,
        "z": 0
      },
      "bodyPart": "left-foot",
      "goalMouthLocation": "right",
      "goalMouthCoordinates": {
        "x": 0,
        "y": 39.2,
        "z": 9.7
      },
      "blockCoordinates": {
        "x": 11.2,
        "y": 52.2,
        "z": 0
      },
      "xg": 0.084288537502289,
      "id": 2083676,
      "time": 8,
      "timeSeconds": 453,
      "draw": {
        "start": {
          "x": 45.8,
          "y": 15.2
        },
        "block": {
          "x": 52.2,
          "y": 11.2
        },
        "end": {
          "x": 60.8,
          "y": 0
        },
        "goal": {
          "x": 60.8,
          "y": 90.3
        }
      },
      "reversedPeriodTime": 38,
      "reversedPeriodTimeSeconds": 2247,
      "incidentType": "shot"
    },
    {
      "player": {
        "name": "Thaciano",
        "slug": "thaciano",
        "shortName": "Thaciano",
        "position": "M",
        "userCount": 438,
        "id": 872039,
        "fieldTranslations": {
          "nameTranslation": {
            "ar": "ثاسيانو"
          },
          "shortNameTranslation": {}
        }
      },
      "isHome": true,
      "shotType": "block",
      "situation": "fast-break",
      "playerCoordinates": {
        "x": 15.2,
        "y": 35.4,
        "z": 0
      },
      "bodyPart": "right-foot",
      "goalMouthLocation": "low-centre",
      "goalMouthCoordinates": {
        "x": 0,
        "y": 51.3,
        "z": 19
      },
      "blockCoordinates": {
        "x": 13.6,
        "y": 36.8,
        "z": 0
      },
      "xg": 0.063353016972542,
      "id": 2083665,
      "time": 5,
      "timeSeconds": 263,
      "draw": {
        "start": {
          "x": 35.4,
          "y": 15.2
        },
        "block": {
          "x": 36.8,
          "y": 13.6
        },
        "end": {
          "x": 48.7,
          "y": 0
        },
        "goal": {
          "x": 48.7,
          "y": 81
        }
      },
      "reversedPeriodTime": 41,
      "reversedPeriodTimeSeconds": 2437,
      "incidentType": "shot"
    }
  ]
}